{"numTotalTestSuites":6,"numPassedTestSuites":2,"numFailedTestSuites":4,"numPendingTestSuites":0,"numTotalTests":160,"numPassedTests":134,"numFailedTests":26,"numPendingTests":0,"numTodoTests":0,"snapshot":{"added":0,"failure":false,"filesAdded":0,"filesRemoved":0,"filesRemovedList":[],"filesUnmatched":0,"filesUpdated":0,"matched":0,"total":0,"unchecked":0,"uncheckedKeysByFile":[],"unmatched":0,"updated":0,"didUpdate":false},"startTime":1773057518338,"success":false,"testResults":[{"assertionResults":[{"ancestorTitles":["Exercício 01"],"fullName":"Exercício 01 Ex01 - Válida - Questão 1","status":"passed","title":"Ex01 - Válida - Questão 1","duration":4.95599900000002,"failureMessages":[],"meta":{}},{"ancestorTitles":["Exercício 01"],"fullName":"Exercício 01 Ex01 - Correta - Questão 1","status":"passed","title":"Ex01 - Correta - Questão 1","duration":1.0329449999999838,"failureMessages":[],"meta":{}},{"ancestorTitles":["Exercício 01"],"fullName":"Exercício 01 Ex01 - Válida - Questão 2","status":"passed","title":"Ex01 - Válida - Questão 2","duration":0.6616190000000302,"failureMessages":[],"meta":{}},{"ancestorTitles":["Exercício 01"],"fullName":"Exercício 01 Ex01 - Correta - Questão 2","status":"passed","title":"Ex01 - Correta - Questão 2","duration":1.7214230000000157,"failureMessages":[],"meta":{}},{"ancestorTitles":["Exercício 01"],"fullName":"Exercício 01 Ex01 - Válida - Questão 3","status":"passed","title":"Ex01 - Válida - Questão 3","duration":0.5364600000000337,"failureMessages":[],"meta":{}},{"ancestorTitles":["Exercício 01"],"fullName":"Exercício 01 Ex01 - Correta - Questão 3","status":"passed","title":"Ex01 - Correta - Questão 3","duration":0.39390100000002803,"failureMessages":[],"meta":{}},{"ancestorTitles":["Exercício 01"],"fullName":"Exercício 01 Ex01 - Válida - Questão 4","status":"passed","title":"Ex01 - Válida - Questão 4","duration":0.8680919999999901,"failureMessages":[],"meta":{}},{"ancestorTitles":["Exercício 01"],"fullName":"Exercício 01 Ex01 - Correta - Questão 4","status":"passed","title":"Ex01 - Correta - Questão 4","duration":0.4964840000000095,"failureMessages":[],"meta":{}},{"ancestorTitles":["Exercício 01"],"fullName":"Exercício 01 Ex01 - Válida - Questão 5","status":"passed","title":"Ex01 - Válida - Questão 5","duration":1.3540560000000141,"failureMessages":[],"meta":{}},{"ancestorTitles":["Exercício 01"],"fullName":"Exercício 01 Ex01 - Correta - Questão 5","status":"passed","title":"Ex01 - Correta - Questão 5","duration":0.597878000000037,"failureMessages":[],"meta":{}},{"ancestorTitles":["Exercício 01"],"fullName":"Exercício 01 Ex01 - Válida - Questão 6","status":"passed","title":"Ex01 - Válida - Questão 6","duration":0.31978499999996757,"failureMessages":[],"meta":{}},{"ancestorTitles":["Exercício 01"],"fullName":"Exercício 01 Ex01 - Correta - Questão 6","status":"passed","title":"Ex01 - Correta - Questão 6","duration":0.18645699999996168,"failureMessages":[],"meta":{}},{"ancestorTitles":["Exercício 01"],"fullName":"Exercício 01 Ex01 - Válida - Questão 7","status":"passed","title":"Ex01 - Válida - Questão 7","duration":0.42903600000005326,"failureMessages":[],"meta":{}},{"ancestorTitles":["Exercício 01"],"fullName":"Exercício 01 Ex01 - Correta - Questão 7","status":"passed","title":"Ex01 - Correta - Questão 7","duration":0.1809570000000349,"failureMessages":[],"meta":{}},{"ancestorTitles":["Exercício 01"],"fullName":"Exercício 01 Ex01 - Válida - Questão 8","status":"passed","title":"Ex01 - Válida - Questão 8","duration":0.2139829999999847,"failureMessages":[],"meta":{}},{"ancestorTitles":["Exercício 01"],"fullName":"Exercício 01 Ex01 - Correta - Questão 8","status":"passed","title":"Ex01 - Correta - Questão 8","duration":0.3023989999999799,"failureMessages":[],"meta":{}},{"ancestorTitles":["Exercício 01"],"fullName":"Exercício 01 Ex01 - Válida - Questão 9","status":"passed","title":"Ex01 - Válida - Questão 9","duration":0.21448700000001963,"failureMessages":[],"meta":{}},{"ancestorTitles":["Exercício 01"],"fullName":"Exercício 01 Ex01 - Correta - Questão 9","status":"passed","title":"Ex01 - Correta - Questão 9","duration":0.16675200000003088,"failureMessages":[],"meta":{}},{"ancestorTitles":["Exercício 01"],"fullName":"Exercício 01 Ex01 - Válida - Questão 10","status":"failed","title":"Ex01 - Válida - Questão 10","duration":26.51707399999998,"failureMessages":["AssertionError: expected undefined to be type of 'boolean'\n    at /home/vicmca/CodeProjects/School/materiais/atividades/3c-rev-01/exercicios.test.js:28:30\n    at file:///home/vicmca/CodeProjects/School/materiais/atividades/3c-rev-01/node_modules/@vitest/runner/dist/index.js:145:11\n    at file:///home/vicmca/CodeProjects/School/materiais/atividades/3c-rev-01/node_modules/@vitest/runner/dist/index.js:915:26\n    at file:///home/vicmca/CodeProjects/School/materiais/atividades/3c-rev-01/node_modules/@vitest/runner/dist/index.js:1243:20\n    at new Promise (<anonymous>)\n    at runWithTimeout (file:///home/vicmca/CodeProjects/School/materiais/atividades/3c-rev-01/node_modules/@vitest/runner/dist/index.js:1209:10)\n    at file:///home/vicmca/CodeProjects/School/materiais/atividades/3c-rev-01/node_modules/@vitest/runner/dist/index.js:1653:37\n    at Traces.$ (file:///home/vicmca/CodeProjects/School/materiais/atividades/3c-rev-01/node_modules/vitest/dist/chunks/traces.CCmnQaNT.js:142:27)\n    at trace (file:///home/vicmca/CodeProjects/School/materiais/atividades/3c-rev-01/node_modules/vitest/dist/chunks/test.B8ej_ZHS.js:239:21)\n    at runTest (file:///home/vicmca/CodeProjects/School/materiais/atividades/3c-rev-01/node_modules/@vitest/runner/dist/index.js:1653:12)"],"meta":{}},{"ancestorTitles":["Exercício 01"],"fullName":"Exercício 01 Ex01 - Correta - Questão 10","status":"failed","title":"Ex01 - Correta - Questão 10","duration":8.142187000000035,"failureMessages":["AssertionError: expected undefined to be type of 'boolean'\n    at /home/vicmca/CodeProjects/School/materiais/atividades/3c-rev-01/exercicios.test.js:32:30\n    at file:///home/vicmca/CodeProjects/School/materiais/atividades/3c-rev-01/node_modules/@vitest/runner/dist/index.js:145:11\n    at file:///home/vicmca/CodeProjects/School/materiais/atividades/3c-rev-01/node_modules/@vitest/runner/dist/index.js:915:26\n    at file:///home/vicmca/CodeProjects/School/materiais/atividades/3c-rev-01/node_modules/@vitest/runner/dist/index.js:1243:20\n    at new Promise (<anonymous>)\n    at runWithTimeout (file:///home/vicmca/CodeProjects/School/materiais/atividades/3c-rev-01/node_modules/@vitest/runner/dist/index.js:1209:10)\n    at file:///home/vicmca/CodeProjects/School/materiais/atividades/3c-rev-01/node_modules/@vitest/runner/dist/index.js:1653:37\n    at Traces.$ (file:///home/vicmca/CodeProjects/School/materiais/atividades/3c-rev-01/node_modules/vitest/dist/chunks/traces.CCmnQaNT.js:142:27)\n    at trace (file:///home/vicmca/CodeProjects/School/materiais/atividades/3c-rev-01/node_modules/vitest/dist/chunks/test.B8ej_ZHS.js:239:21)\n    at runTest (file:///home/vicmca/CodeProjects/School/materiais/atividades/3c-rev-01/node_modules/@vitest/runner/dist/index.js:1653:12)"],"meta":{}},{"ancestorTitles":["Exercício 01"],"fullName":"Exercício 01 Ex01 - Válida - Questão 11","status":"passed","title":"Ex01 - Válida - Questão 11","duration":0.49994199999991906,"failureMessages":[],"meta":{}},{"ancestorTitles":["Exercício 01"],"fullName":"Exercício 01 Ex01 - Correta - Questão 11","status":"passed","title":"Ex01 - Correta - Questão 11","duration":0.2459039999999959,"failureMessages":[],"meta":{}},{"ancestorTitles":["Exercício 01"],"fullName":"Exercício 01 Ex01 - Válida - Questão 12","status":"passed","title":"Ex01 - Válida - Questão 12","duration":0.2883559999999079,"failureMessages":[],"meta":{}},{"ancestorTitles":["Exercício 01"],"fullName":"Exercício 01 Ex01 - Correta - Questão 12","status":"passed","title":"Ex01 - Correta - Questão 12","duration":0.21972999999991316,"failureMessages":[],"meta":{}},{"ancestorTitles":["Exercício 01"],"fullName":"Exercício 01 Ex01 - Válida - Questão 13","status":"passed","title":"Ex01 - Válida - Questão 13","duration":0.332396000000017,"failureMessages":[],"meta":{}},{"ancestorTitles":["Exercício 01"],"fullName":"Exercício 01 Ex01 - Correta - Questão 13","status":"passed","title":"Ex01 - Correta - Questão 13","duration":0.21452799999997296,"failureMessages":[],"meta":{}},{"ancestorTitles":["Exercício 01"],"fullName":"Exercício 01 Ex01 - Válida - Questão 14","status":"passed","title":"Ex01 - Válida - Questão 14","duration":0.287873999999988,"failureMessages":[],"meta":{}},{"ancestorTitles":["Exercício 01"],"fullName":"Exercício 01 Ex01 - Correta - Questão 14","status":"passed","title":"Ex01 - Correta - Questão 14","duration":0.23334799999997813,"failureMessages":[],"meta":{}},{"ancestorTitles":["Exercício 01"],"fullName":"Exercício 01 Ex01 - Válida - Questão 15","status":"failed","title":"Ex01 - Válida - Questão 15","duration":2.627599999999916,"failureMessages":["AssertionError: expected undefined to be type of 'function'\n    at /home/vicmca/CodeProjects/School/materiais/atividades/3c-rev-01/exercicios.test.js:28:30\n    at file:///home/vicmca/CodeProjects/School/materiais/atividades/3c-rev-01/node_modules/@vitest/runner/dist/index.js:145:11\n    at file:///home/vicmca/CodeProjects/School/materiais/atividades/3c-rev-01/node_modules/@vitest/runner/dist/index.js:915:26\n    at file:///home/vicmca/CodeProjects/School/materiais/atividades/3c-rev-01/node_modules/@vitest/runner/dist/index.js:1243:20\n    at new Promise (<anonymous>)\n    at runWithTimeout (file:///home/vicmca/CodeProjects/School/materiais/atividades/3c-rev-01/node_modules/@vitest/runner/dist/index.js:1209:10)\n    at file:///home/vicmca/CodeProjects/School/materiais/atividades/3c-rev-01/node_modules/@vitest/runner/dist/index.js:1653:37\n    at Traces.$ (file:///home/vicmca/CodeProjects/School/materiais/atividades/3c-rev-01/node_modules/vitest/dist/chunks/traces.CCmnQaNT.js:142:27)\n    at trace (file:///home/vicmca/CodeProjects/School/materiais/atividades/3c-rev-01/node_modules/vitest/dist/chunks/test.B8ej_ZHS.js:239:21)\n    at runTest (file:///home/vicmca/CodeProjects/School/materiais/atividades/3c-rev-01/node_modules/@vitest/runner/dist/index.js:1653:12)"],"meta":{}},{"ancestorTitles":["Exercício 01"],"fullName":"Exercício 01 Ex01 - Correta - Questão 15","status":"failed","title":"Ex01 - Correta - Questão 15","duration":2.156170999999972,"failureMessages":["AssertionError: expected undefined to be type of 'function'\n    at /home/vicmca/CodeProjects/School/materiais/atividades/3c-rev-01/exercicios.test.js:32:30\n    at file:///home/vicmca/CodeProjects/School/materiais/atividades/3c-rev-01/node_modules/@vitest/runner/dist/index.js:145:11\n    at file:///home/vicmca/CodeProjects/School/materiais/atividades/3c-rev-01/node_modules/@vitest/runner/dist/index.js:915:26\n    at file:///home/vicmca/CodeProjects/School/materiais/atividades/3c-rev-01/node_modules/@vitest/runner/dist/index.js:1243:20\n    at new Promise (<anonymous>)\n    at runWithTimeout (file:///home/vicmca/CodeProjects/School/materiais/atividades/3c-rev-01/node_modules/@vitest/runner/dist/index.js:1209:10)\n    at file:///home/vicmca/CodeProjects/School/materiais/atividades/3c-rev-01/node_modules/@vitest/runner/dist/index.js:1653:37\n    at Traces.$ (file:///home/vicmca/CodeProjects/School/materiais/atividades/3c-rev-01/node_modules/vitest/dist/chunks/traces.CCmnQaNT.js:142:27)\n    at trace (file:///home/vicmca/CodeProjects/School/materiais/atividades/3c-rev-01/node_modules/vitest/dist/chunks/test.B8ej_ZHS.js:239:21)\n    at runTest (file:///home/vicmca/CodeProjects/School/materiais/atividades/3c-rev-01/node_modules/@vitest/runner/dist/index.js:1653:12)"],"meta":{}},{"ancestorTitles":["Exercício 01"],"fullName":"Exercício 01 Ex01 - Válida - Questão 16","status":"failed","title":"Ex01 - Válida - Questão 16","duration":2.0041769999999133,"failureMessages":["AssertionError: expected undefined to be type of 'boolean'\n    at /home/vicmca/CodeProjects/School/materiais/atividades/3c-rev-01/exercicios.test.js:28:30\n    at file:///home/vicmca/CodeProjects/School/materiais/atividades/3c-rev-01/node_modules/@vitest/runner/dist/index.js:145:11\n    at file:///home/vicmca/CodeProjects/School/materiais/atividades/3c-rev-01/node_modules/@vitest/runner/dist/index.js:915:26\n    at file:///home/vicmca/CodeProjects/School/materiais/atividades/3c-rev-01/node_modules/@vitest/runner/dist/index.js:1243:20\n    at new Promise (<anonymous>)\n    at runWithTimeout (file:///home/vicmca/CodeProjects/School/materiais/atividades/3c-rev-01/node_modules/@vitest/runner/dist/index.js:1209:10)\n    at file:///home/vicmca/CodeProjects/School/materiais/atividades/3c-rev-01/node_modules/@vitest/runner/dist/index.js:1653:37\n    at Traces.$ (file:///home/vicmca/CodeProjects/School/materiais/atividades/3c-rev-01/node_modules/vitest/dist/chunks/traces.CCmnQaNT.js:142:27)\n    at trace (file:///home/vicmca/CodeProjects/School/materiais/atividades/3c-rev-01/node_modules/vitest/dist/chunks/test.B8ej_ZHS.js:239:21)\n    at runTest (file:///home/vicmca/CodeProjects/School/materiais/atividades/3c-rev-01/node_modules/@vitest/runner/dist/index.js:1653:12)"],"meta":{}},{"ancestorTitles":["Exercício 01"],"fullName":"Exercício 01 Ex01 - Correta - Questão 16","status":"failed","title":"Ex01 - Correta - Questão 16","duration":1.495162999999934,"failureMessages":["AssertionError: expected undefined to be type of 'boolean'\n    at /home/vicmca/CodeProjects/School/materiais/atividades/3c-rev-01/exercicios.test.js:32:30\n    at file:///home/vicmca/CodeProjects/School/materiais/atividades/3c-rev-01/node_modules/@vitest/runner/dist/index.js:145:11\n    at file:///home/vicmca/CodeProjects/School/materiais/atividades/3c-rev-01/node_modules/@vitest/runner/dist/index.js:915:26\n    at file:///home/vicmca/CodeProjects/School/materiais/atividades/3c-rev-01/node_modules/@vitest/runner/dist/index.js:1243:20\n    at new Promise (<anonymous>)\n    at runWithTimeout (file:///home/vicmca/CodeProjects/School/materiais/atividades/3c-rev-01/node_modules/@vitest/runner/dist/index.js:1209:10)\n    at file:///home/vicmca/CodeProjects/School/materiais/atividades/3c-rev-01/node_modules/@vitest/runner/dist/index.js:1653:37\n    at Traces.$ (file:///home/vicmca/CodeProjects/School/materiais/atividades/3c-rev-01/node_modules/vitest/dist/chunks/traces.CCmnQaNT.js:142:27)\n    at trace (file:///home/vicmca/CodeProjects/School/materiais/atividades/3c-rev-01/node_modules/vitest/dist/chunks/test.B8ej_ZHS.js:239:21)\n    at runTest (file:///home/vicmca/CodeProjects/School/materiais/atividades/3c-rev-01/node_modules/@vitest/runner/dist/index.js:1653:12)"],"meta":{}},{"ancestorTitles":["Exercício 01"],"fullName":"Exercício 01 Ex01 - Válida - Questão 17","status":"failed","title":"Ex01 - Válida - Questão 17","duration":1.107293000000027,"failureMessages":["AssertionError: expected undefined to be type of 'boolean'\n    at /home/vicmca/CodeProjects/School/materiais/atividades/3c-rev-01/exercicios.test.js:28:30\n    at file:///home/vicmca/CodeProjects/School/materiais/atividades/3c-rev-01/node_modules/@vitest/runner/dist/index.js:145:11\n    at file:///home/vicmca/CodeProjects/School/materiais/atividades/3c-rev-01/node_modules/@vitest/runner/dist/index.js:915:26\n    at file:///home/vicmca/CodeProjects/School/materiais/atividades/3c-rev-01/node_modules/@vitest/runner/dist/index.js:1243:20\n    at new Promise (<anonymous>)\n    at runWithTimeout (file:///home/vicmca/CodeProjects/School/materiais/atividades/3c-rev-01/node_modules/@vitest/runner/dist/index.js:1209:10)\n    at file:///home/vicmca/CodeProjects/School/materiais/atividades/3c-rev-01/node_modules/@vitest/runner/dist/index.js:1653:37\n    at Traces.$ (file:///home/vicmca/CodeProjects/School/materiais/atividades/3c-rev-01/node_modules/vitest/dist/chunks/traces.CCmnQaNT.js:142:27)\n    at trace (file:///home/vicmca/CodeProjects/School/materiais/atividades/3c-rev-01/node_modules/vitest/dist/chunks/test.B8ej_ZHS.js:239:21)\n    at runTest (file:///home/vicmca/CodeProjects/School/materiais/atividades/3c-rev-01/node_modules/@vitest/runner/dist/index.js:1653:12)"],"meta":{}},{"ancestorTitles":["Exercício 01"],"fullName":"Exercício 01 Ex01 - Correta - Questão 17","status":"failed","title":"Ex01 - Correta - Questão 17","duration":1.0194099999999935,"failureMessages":["AssertionError: expected undefined to be type of 'boolean'\n    at /home/vicmca/CodeProjects/School/materiais/atividades/3c-rev-01/exercicios.test.js:32:30\n    at file:///home/vicmca/CodeProjects/School/materiais/atividades/3c-rev-01/node_modules/@vitest/runner/dist/index.js:145:11\n    at file:///home/vicmca/CodeProjects/School/materiais/atividades/3c-rev-01/node_modules/@vitest/runner/dist/index.js:915:26\n    at file:///home/vicmca/CodeProjects/School/materiais/atividades/3c-rev-01/node_modules/@vitest/runner/dist/index.js:1243:20\n    at new Promise (<anonymous>)\n    at runWithTimeout (file:///home/vicmca/CodeProjects/School/materiais/atividades/3c-rev-01/node_modules/@vitest/runner/dist/index.js:1209:10)\n    at file:///home/vicmca/CodeProjects/School/materiais/atividades/3c-rev-01/node_modules/@vitest/runner/dist/index.js:1653:37\n    at Traces.$ (file:///home/vicmca/CodeProjects/School/materiais/atividades/3c-rev-01/node_modules/vitest/dist/chunks/traces.CCmnQaNT.js:142:27)\n    at trace (file:///home/vicmca/CodeProjects/School/materiais/atividades/3c-rev-01/node_modules/vitest/dist/chunks/test.B8ej_ZHS.js:239:21)\n    at runTest (file:///home/vicmca/CodeProjects/School/materiais/atividades/3c-rev-01/node_modules/@vitest/runner/dist/index.js:1653:12)"],"meta":{}},{"ancestorTitles":["Exercício 01"],"fullName":"Exercício 01 Ex01 - Válida - Questão 18","status":"failed","title":"Ex01 - Válida - Questão 18","duration":1.8717909999999165,"failureMessages":["AssertionError: expected undefined to be type of 'boolean'\n    at /home/vicmca/CodeProjects/School/materiais/atividades/3c-rev-01/exercicios.test.js:28:30\n    at file:///home/vicmca/CodeProjects/School/materiais/atividades/3c-rev-01/node_modules/@vitest/runner/dist/index.js:145:11\n    at file:///home/vicmca/CodeProjects/School/materiais/atividades/3c-rev-01/node_modules/@vitest/runner/dist/index.js:915:26\n    at file:///home/vicmca/CodeProjects/School/materiais/atividades/3c-rev-01/node_modules/@vitest/runner/dist/index.js:1243:20\n    at new Promise (<anonymous>)\n    at runWithTimeout (file:///home/vicmca/CodeProjects/School/materiais/atividades/3c-rev-01/node_modules/@vitest/runner/dist/index.js:1209:10)\n    at file:///home/vicmca/CodeProjects/School/materiais/atividades/3c-rev-01/node_modules/@vitest/runner/dist/index.js:1653:37\n    at Traces.$ (file:///home/vicmca/CodeProjects/School/materiais/atividades/3c-rev-01/node_modules/vitest/dist/chunks/traces.CCmnQaNT.js:142:27)\n    at trace (file:///home/vicmca/CodeProjects/School/materiais/atividades/3c-rev-01/node_modules/vitest/dist/chunks/test.B8ej_ZHS.js:239:21)\n    at runTest (file:///home/vicmca/CodeProjects/School/materiais/atividades/3c-rev-01/node_modules/@vitest/runner/dist/index.js:1653:12)"],"meta":{}},{"ancestorTitles":["Exercício 01"],"fullName":"Exercício 01 Ex01 - Correta - Questão 18","status":"failed","title":"Ex01 - Correta - Questão 18","duration":1.7155870000000277,"failureMessages":["AssertionError: expected undefined to be type of 'boolean'\n    at /home/vicmca/CodeProjects/School/materiais/atividades/3c-rev-01/exercicios.test.js:32:30\n    at file:///home/vicmca/CodeProjects/School/materiais/atividades/3c-rev-01/node_modules/@vitest/runner/dist/index.js:145:11\n    at file:///home/vicmca/CodeProjects/School/materiais/atividades/3c-rev-01/node_modules/@vitest/runner/dist/index.js:915:26\n    at file:///home/vicmca/CodeProjects/School/materiais/atividades/3c-rev-01/node_modules/@vitest/runner/dist/index.js:1243:20\n    at new Promise (<anonymous>)\n    at runWithTimeout (file:///home/vicmca/CodeProjects/School/materiais/atividades/3c-rev-01/node_modules/@vitest/runner/dist/index.js:1209:10)\n    at file:///home/vicmca/CodeProjects/School/materiais/atividades/3c-rev-01/node_modules/@vitest/runner/dist/index.js:1653:37\n    at Traces.$ (file:///home/vicmca/CodeProjects/School/materiais/atividades/3c-rev-01/node_modules/vitest/dist/chunks/traces.CCmnQaNT.js:142:27)\n    at trace (file:///home/vicmca/CodeProjects/School/materiais/atividades/3c-rev-01/node_modules/vitest/dist/chunks/test.B8ej_ZHS.js:239:21)\n    at runTest (file:///home/vicmca/CodeProjects/School/materiais/atividades/3c-rev-01/node_modules/@vitest/runner/dist/index.js:1653:12)"],"meta":{}},{"ancestorTitles":["Exercício 01"],"fullName":"Exercício 01 Ex01 - Válida - Questão 19","status":"failed","title":"Ex01 - Válida - Questão 19","duration":0.9831570000000056,"failureMessages":["AssertionError: expected undefined to be type of 'boolean'\n    at /home/vicmca/CodeProjects/School/materiais/atividades/3c-rev-01/exercicios.test.js:28:30\n    at file:///home/vicmca/CodeProjects/School/materiais/atividades/3c-rev-01/node_modules/@vitest/runner/dist/index.js:145:11\n    at file:///home/vicmca/CodeProjects/School/materiais/atividades/3c-rev-01/node_modules/@vitest/runner/dist/index.js:915:26\n    at file:///home/vicmca/CodeProjects/School/materiais/atividades/3c-rev-01/node_modules/@vitest/runner/dist/index.js:1243:20\n    at new Promise (<anonymous>)\n    at runWithTimeout (file:///home/vicmca/CodeProjects/School/materiais/atividades/3c-rev-01/node_modules/@vitest/runner/dist/index.js:1209:10)\n    at file:///home/vicmca/CodeProjects/School/materiais/atividades/3c-rev-01/node_modules/@vitest/runner/dist/index.js:1653:37\n    at Traces.$ (file:///home/vicmca/CodeProjects/School/materiais/atividades/3c-rev-01/node_modules/vitest/dist/chunks/traces.CCmnQaNT.js:142:27)\n    at trace (file:///home/vicmca/CodeProjects/School/materiais/atividades/3c-rev-01/node_modules/vitest/dist/chunks/test.B8ej_ZHS.js:239:21)\n    at runTest (file:///home/vicmca/CodeProjects/School/materiais/atividades/3c-rev-01/node_modules/@vitest/runner/dist/index.js:1653:12)"],"meta":{}},{"ancestorTitles":["Exercício 01"],"fullName":"Exercício 01 Ex01 - Correta - Questão 19","status":"failed","title":"Ex01 - Correta - Questão 19","duration":0.8130979999999681,"failureMessages":["AssertionError: expected undefined to be type of 'boolean'\n    at /home/vicmca/CodeProjects/School/materiais/atividades/3c-rev-01/exercicios.test.js:32:30\n    at file:///home/vicmca/CodeProjects/School/materiais/atividades/3c-rev-01/node_modules/@vitest/runner/dist/index.js:145:11\n    at file:///home/vicmca/CodeProjects/School/materiais/atividades/3c-rev-01/node_modules/@vitest/runner/dist/index.js:915:26\n    at file:///home/vicmca/CodeProjects/School/materiais/atividades/3c-rev-01/node_modules/@vitest/runner/dist/index.js:1243:20\n    at new Promise (<anonymous>)\n    at runWithTimeout (file:///home/vicmca/CodeProjects/School/materiais/atividades/3c-rev-01/node_modules/@vitest/runner/dist/index.js:1209:10)\n    at file:///home/vicmca/CodeProjects/School/materiais/atividades/3c-rev-01/node_modules/@vitest/runner/dist/index.js:1653:37\n    at Traces.$ (file:///home/vicmca/CodeProjects/School/materiais/atividades/3c-rev-01/node_modules/vitest/dist/chunks/traces.CCmnQaNT.js:142:27)\n    at trace (file:///home/vicmca/CodeProjects/School/materiais/atividades/3c-rev-01/node_modules/vitest/dist/chunks/test.B8ej_ZHS.js:239:21)\n    at runTest (file:///home/vicmca/CodeProjects/School/materiais/atividades/3c-rev-01/node_modules/@vitest/runner/dist/index.js:1653:12)"],"meta":{}},{"ancestorTitles":["Exercício 01"],"fullName":"Exercício 01 Ex01 - Válida - Questão 20","status":"failed","title":"Ex01 - Válida - Questão 20","duration":0.9896790000000237,"failureMessages":["AssertionError: expected undefined to be type of 'function'\n    at /home/vicmca/CodeProjects/School/materiais/atividades/3c-rev-01/exercicios.test.js:28:30\n    at file:///home/vicmca/CodeProjects/School/materiais/atividades/3c-rev-01/node_modules/@vitest/runner/dist/index.js:145:11\n    at file:///home/vicmca/CodeProjects/School/materiais/atividades/3c-rev-01/node_modules/@vitest/runner/dist/index.js:915:26\n    at file:///home/vicmca/CodeProjects/School/materiais/atividades/3c-rev-01/node_modules/@vitest/runner/dist/index.js:1243:20\n    at new Promise (<anonymous>)\n    at runWithTimeout (file:///home/vicmca/CodeProjects/School/materiais/atividades/3c-rev-01/node_modules/@vitest/runner/dist/index.js:1209:10)\n    at file:///home/vicmca/CodeProjects/School/materiais/atividades/3c-rev-01/node_modules/@vitest/runner/dist/index.js:1653:37\n    at Traces.$ (file:///home/vicmca/CodeProjects/School/materiais/atividades/3c-rev-01/node_modules/vitest/dist/chunks/traces.CCmnQaNT.js:142:27)\n    at trace (file:///home/vicmca/CodeProjects/School/materiais/atividades/3c-rev-01/node_modules/vitest/dist/chunks/test.B8ej_ZHS.js:239:21)\n    at runTest (file:///home/vicmca/CodeProjects/School/materiais/atividades/3c-rev-01/node_modules/@vitest/runner/dist/index.js:1653:12)"],"meta":{}},{"ancestorTitles":["Exercício 01"],"fullName":"Exercício 01 Ex01 - Correta - Questão 20","status":"failed","title":"Ex01 - Correta - Questão 20","duration":0.7634019999999282,"failureMessages":["AssertionError: expected undefined to be type of 'function'\n    at /home/vicmca/CodeProjects/School/materiais/atividades/3c-rev-01/exercicios.test.js:32:30\n    at file:///home/vicmca/CodeProjects/School/materiais/atividades/3c-rev-01/node_modules/@vitest/runner/dist/index.js:145:11\n    at file:///home/vicmca/CodeProjects/School/materiais/atividades/3c-rev-01/node_modules/@vitest/runner/dist/index.js:915:26\n    at file:///home/vicmca/CodeProjects/School/materiais/atividades/3c-rev-01/node_modules/@vitest/runner/dist/index.js:1243:20\n    at new Promise (<anonymous>)\n    at runWithTimeout (file:///home/vicmca/CodeProjects/School/materiais/atividades/3c-rev-01/node_modules/@vitest/runner/dist/index.js:1209:10)\n    at file:///home/vicmca/CodeProjects/School/materiais/atividades/3c-rev-01/node_modules/@vitest/runner/dist/index.js:1653:37\n    at Traces.$ (file:///home/vicmca/CodeProjects/School/materiais/atividades/3c-rev-01/node_modules/vitest/dist/chunks/traces.CCmnQaNT.js:142:27)\n    at trace (file:///home/vicmca/CodeProjects/School/materiais/atividades/3c-rev-01/node_modules/vitest/dist/chunks/test.B8ej_ZHS.js:239:21)\n    at runTest (file:///home/vicmca/CodeProjects/School/materiais/atividades/3c-rev-01/node_modules/@vitest/runner/dist/index.js:1653:12)"],"meta":{}},{"ancestorTitles":["Exercício 02"],"fullName":"Exercício 02 Ex02 - Válida - Questão 1","status":"passed","title":"Ex02 - Válida - Questão 1","duration":0.4931139999999914,"failureMessages":[],"meta":{}},{"ancestorTitles":["Exercício 02"],"fullName":"Exercício 02 Ex02 - Correta - Questão 1","status":"passed","title":"Ex02 - Correta - Questão 1","duration":0.279280999999969,"failureMessages":[],"meta":{}},{"ancestorTitles":["Exercício 02"],"fullName":"Exercício 02 Ex02 - Válida - Questão 2","status":"failed","title":"Ex02 - Válida - Questão 2","duration":1.5646299999999655,"failureMessages":["AssertionError: expected [Function Object] to be type of 'object'\n    at /home/vicmca/CodeProjects/School/materiais/atividades/3c-rev-01/exercicios.test.js:60:30\n    at file:///home/vicmca/CodeProjects/School/materiais/atividades/3c-rev-01/node_modules/@vitest/runner/dist/index.js:145:11\n    at file:///home/vicmca/CodeProjects/School/materiais/atividades/3c-rev-01/node_modules/@vitest/runner/dist/index.js:915:26\n    at file:///home/vicmca/CodeProjects/School/materiais/atividades/3c-rev-01/node_modules/@vitest/runner/dist/index.js:1243:20\n    at new Promise (<anonymous>)\n    at runWithTimeout (file:///home/vicmca/CodeProjects/School/materiais/atividades/3c-rev-01/node_modules/@vitest/runner/dist/index.js:1209:10)\n    at file:///home/vicmca/CodeProjects/School/materiais/atividades/3c-rev-01/node_modules/@vitest/runner/dist/index.js:1653:37\n    at Traces.$ (file:///home/vicmca/CodeProjects/School/materiais/atividades/3c-rev-01/node_modules/vitest/dist/chunks/traces.CCmnQaNT.js:142:27)\n    at trace (file:///home/vicmca/CodeProjects/School/materiais/atividades/3c-rev-01/node_modules/vitest/dist/chunks/test.B8ej_ZHS.js:239:21)\n    at runTest (file:///home/vicmca/CodeProjects/School/materiais/atividades/3c-rev-01/node_modules/@vitest/runner/dist/index.js:1653:12)"],"meta":{}},{"ancestorTitles":["Exercício 02"],"fullName":"Exercício 02 Ex02 - Correta - Questão 2","status":"passed","title":"Ex02 - Correta - Questão 2","duration":0.2795259999999189,"failureMessages":[],"meta":{}},{"ancestorTitles":["Exercício 02"],"fullName":"Exercício 02 Ex02 - Válida - Questão 3","status":"passed","title":"Ex02 - Válida - Questão 3","duration":0.3220139999999674,"failureMessages":[],"meta":{}},{"ancestorTitles":["Exercício 02"],"fullName":"Exercício 02 Ex02 - Correta - Questão 3","status":"passed","title":"Ex02 - Correta - Questão 3","duration":0.4036310000000185,"failureMessages":[],"meta":{}},{"ancestorTitles":["Exercício 02"],"fullName":"Exercício 02 Ex02 - Válida - Questão 4","status":"passed","title":"Ex02 - Válida - Questão 4","duration":0.28544699999997647,"failureMessages":[],"meta":{}},{"ancestorTitles":["Exercício 02"],"fullName":"Exercício 02 Ex02 - Correta - Questão 4","status":"passed","title":"Ex02 - Correta - Questão 4","duration":0.19047100000000228,"failureMessages":[],"meta":{}},{"ancestorTitles":["Exercício 02"],"fullName":"Exercício 02 Ex02 - Válida - Questão 5","status":"passed","title":"Ex02 - Válida - Questão 5","duration":0.38136199999996734,"failureMessages":[],"meta":{}},{"ancestorTitles":["Exercício 02"],"fullName":"Exercício 02 Ex02 - Correta - Questão 5","status":"passed","title":"Ex02 - Correta - Questão 5","duration":0.2176560000000336,"failureMessages":[],"meta":{}},{"ancestorTitles":["Exercício 02"],"fullName":"Exercício 02 Ex02 - Válida - Questão 6","status":"passed","title":"Ex02 - Válida - Questão 6","duration":0.28997400000002926,"failureMessages":[],"meta":{}},{"ancestorTitles":["Exercício 02"],"fullName":"Exercício 02 Ex02 - Correta - Questão 6","status":"passed","title":"Ex02 - Correta - Questão 6","duration":0.18098699999995915,"failureMessages":[],"meta":{}},{"ancestorTitles":["Exercício 02"],"fullName":"Exercício 02 Ex02 - Válida - Questão 7","status":"passed","title":"Ex02 - Válida - Questão 7","duration":0.25173100000006343,"failureMessages":[],"meta":{}},{"ancestorTitles":["Exercício 02"],"fullName":"Exercício 02 Ex02 - Correta - Questão 7","status":"passed","title":"Ex02 - Correta - Questão 7","duration":0.1858599999999342,"failureMessages":[],"meta":{}},{"ancestorTitles":["Exercício 02"],"fullName":"Exercício 02 Ex02 - Válida - Questão 8","status":"passed","title":"Ex02 - Válida - Questão 8","duration":0.2763039999999819,"failureMessages":[],"meta":{}},{"ancestorTitles":["Exercício 02"],"fullName":"Exercício 02 Ex02 - Correta - Questão 8","status":"passed","title":"Ex02 - Correta - Questão 8","duration":0.1862140000000636,"failureMessages":[],"meta":{}},{"ancestorTitles":["Exercício 02"],"fullName":"Exercício 02 Ex02 - Válida - Questão 9","status":"passed","title":"Ex02 - Válida - Questão 9","duration":0.26379099999996924,"failureMessages":[],"meta":{}},{"ancestorTitles":["Exercício 02"],"fullName":"Exercício 02 Ex02 - Correta - Questão 9","status":"passed","title":"Ex02 - Correta - Questão 9","duration":0.1881620000000339,"failureMessages":[],"meta":{}},{"ancestorTitles":["Exercício 02"],"fullName":"Exercício 02 Ex02 - Válida - Questão 10","status":"passed","title":"Ex02 - Válida - Questão 10","duration":0.25765000000001237,"failureMessages":[],"meta":{}},{"ancestorTitles":["Exercício 02"],"fullName":"Exercício 02 Ex02 - Correta - Questão 10","status":"passed","title":"Ex02 - Correta - Questão 10","duration":0.18826899999999114,"failureMessages":[],"meta":{}},{"ancestorTitles":["Exercício 02"],"fullName":"Exercício 02 Ex02 - Válida - Questão 11","status":"passed","title":"Ex02 - Válida - Questão 11","duration":0.29044100000010076,"failureMessages":[],"meta":{}},{"ancestorTitles":["Exercício 02"],"fullName":"Exercício 02 Ex02 - Correta - Questão 11","status":"passed","title":"Ex02 - Correta - Questão 11","duration":0.19487099999992097,"failureMessages":[],"meta":{}},{"ancestorTitles":["Exercício 02"],"fullName":"Exercício 02 Ex02 - Válida - Questão 12","status":"passed","title":"Ex02 - Válida - Questão 12","duration":0.3077729999999974,"failureMessages":[],"meta":{}},{"ancestorTitles":["Exercício 02"],"fullName":"Exercício 02 Ex02 - Correta - Questão 12","status":"passed","title":"Ex02 - Correta - Questão 12","duration":0.17280000000005202,"failureMessages":[],"meta":{}},{"ancestorTitles":["Exercício 02"],"fullName":"Exercício 02 Ex02 - Válida - Questão 13","status":"passed","title":"Ex02 - Válida - Questão 13","duration":0.2800250000000233,"failureMessages":[],"meta":{}},{"ancestorTitles":["Exercício 02"],"fullName":"Exercício 02 Ex02 - Correta - Questão 13","status":"passed","title":"Ex02 - Correta - Questão 13","duration":0.17957000000001244,"failureMessages":[],"meta":{}},{"ancestorTitles":["Exercício 02"],"fullName":"Exercício 02 Ex02 - Válida - Questão 14","status":"failed","title":"Ex02 - Válida - Questão 14","duration":1.001039999999989,"failureMessages":["AssertionError: expected undefined to be type of 'string'\n    at /home/vicmca/CodeProjects/School/materiais/atividades/3c-rev-01/exercicios.test.js:60:30\n    at file:///home/vicmca/CodeProjects/School/materiais/atividades/3c-rev-01/node_modules/@vitest/runner/dist/index.js:145:11\n    at file:///home/vicmca/CodeProjects/School/materiais/atividades/3c-rev-01/node_modules/@vitest/runner/dist/index.js:915:26\n    at file:///home/vicmca/CodeProjects/School/materiais/atividades/3c-rev-01/node_modules/@vitest/runner/dist/index.js:1243:20\n    at new Promise (<anonymous>)\n    at runWithTimeout (file:///home/vicmca/CodeProjects/School/materiais/atividades/3c-rev-01/node_modules/@vitest/runner/dist/index.js:1209:10)\n    at file:///home/vicmca/CodeProjects/School/materiais/atividades/3c-rev-01/node_modules/@vitest/runner/dist/index.js:1653:37\n    at Traces.$ (file:///home/vicmca/CodeProjects/School/materiais/atividades/3c-rev-01/node_modules/vitest/dist/chunks/traces.CCmnQaNT.js:142:27)\n    at trace (file:///home/vicmca/CodeProjects/School/materiais/atividades/3c-rev-01/node_modules/vitest/dist/chunks/test.B8ej_ZHS.js:239:21)\n    at runTest (file:///home/vicmca/CodeProjects/School/materiais/atividades/3c-rev-01/node_modules/@vitest/runner/dist/index.js:1653:12)"],"meta":{}},{"ancestorTitles":["Exercício 02"],"fullName":"Exercício 02 Ex02 - Correta - Questão 14","status":"passed","title":"Ex02 - Correta - Questão 14","duration":0.15530999999998585,"failureMessages":[],"meta":{}},{"ancestorTitles":["Exercício 02"],"fullName":"Exercício 02 Ex02 - Válida - Questão 15","status":"failed","title":"Ex02 - Válida - Questão 15","duration":0.7872120000000677,"failureMessages":["AssertionError: expected undefined to be type of 'number'\n    at /home/vicmca/CodeProjects/School/materiais/atividades/3c-rev-01/exercicios.test.js:60:30\n    at file:///home/vicmca/CodeProjects/School/materiais/atividades/3c-rev-01/node_modules/@vitest/runner/dist/index.js:145:11\n    at file:///home/vicmca/CodeProjects/School/materiais/atividades/3c-rev-01/node_modules/@vitest/runner/dist/index.js:915:26\n    at file:///home/vicmca/CodeProjects/School/materiais/atividades/3c-rev-01/node_modules/@vitest/runner/dist/index.js:1243:20\n    at new Promise (<anonymous>)\n    at runWithTimeout (file:///home/vicmca/CodeProjects/School/materiais/atividades/3c-rev-01/node_modules/@vitest/runner/dist/index.js:1209:10)\n    at file:///home/vicmca/CodeProjects/School/materiais/atividades/3c-rev-01/node_modules/@vitest/runner/dist/index.js:1653:37\n    at Traces.$ (file:///home/vicmca/CodeProjects/School/materiais/atividades/3c-rev-01/node_modules/vitest/dist/chunks/traces.CCmnQaNT.js:142:27)\n    at trace (file:///home/vicmca/CodeProjects/School/materiais/atividades/3c-rev-01/node_modules/vitest/dist/chunks/test.B8ej_ZHS.js:239:21)\n    at runTest (file:///home/vicmca/CodeProjects/School/materiais/atividades/3c-rev-01/node_modules/@vitest/runner/dist/index.js:1653:12)"],"meta":{}},{"ancestorTitles":["Exercício 02"],"fullName":"Exercício 02 Ex02 - Correta - Questão 15","status":"passed","title":"Ex02 - Correta - Questão 15","duration":0.15133800000000974,"failureMessages":[],"meta":{}},{"ancestorTitles":["Exercício 02"],"fullName":"Exercício 02 Ex02 - Válida - Questão 16","status":"failed","title":"Ex02 - Válida - Questão 16","duration":0.9717210000000023,"failureMessages":["AssertionError: expected undefined to be type of 'boolean'\n    at /home/vicmca/CodeProjects/School/materiais/atividades/3c-rev-01/exercicios.test.js:60:30\n    at file:///home/vicmca/CodeProjects/School/materiais/atividades/3c-rev-01/node_modules/@vitest/runner/dist/index.js:145:11\n    at file:///home/vicmca/CodeProjects/School/materiais/atividades/3c-rev-01/node_modules/@vitest/runner/dist/index.js:915:26\n    at file:///home/vicmca/CodeProjects/School/materiais/atividades/3c-rev-01/node_modules/@vitest/runner/dist/index.js:1243:20\n    at new Promise (<anonymous>)\n    at runWithTimeout (file:///home/vicmca/CodeProjects/School/materiais/atividades/3c-rev-01/node_modules/@vitest/runner/dist/index.js:1209:10)\n    at file:///home/vicmca/CodeProjects/School/materiais/atividades/3c-rev-01/node_modules/@vitest/runner/dist/index.js:1653:37\n    at Traces.$ (file:///home/vicmca/CodeProjects/School/materiais/atividades/3c-rev-01/node_modules/vitest/dist/chunks/traces.CCmnQaNT.js:142:27)\n    at trace (file:///home/vicmca/CodeProjects/School/materiais/atividades/3c-rev-01/node_modules/vitest/dist/chunks/test.B8ej_ZHS.js:239:21)\n    at runTest (file:///home/vicmca/CodeProjects/School/materiais/atividades/3c-rev-01/node_modules/@vitest/runner/dist/index.js:1653:12)"],"meta":{}},{"ancestorTitles":["Exercício 02"],"fullName":"Exercício 02 Ex02 - Correta - Questão 16","status":"passed","title":"Ex02 - Correta - Questão 16","duration":0.22914000000002943,"failureMessages":[],"meta":{}},{"ancestorTitles":["Exercício 02"],"fullName":"Exercício 02 Ex02 - Válida - Questão 17","status":"failed","title":"Ex02 - Válida - Questão 17","duration":1.207883000000038,"failureMessages":["AssertionError: expected undefined to be type of 'string'\n    at /home/vicmca/CodeProjects/School/materiais/atividades/3c-rev-01/exercicios.test.js:60:30\n    at file:///home/vicmca/CodeProjects/School/materiais/atividades/3c-rev-01/node_modules/@vitest/runner/dist/index.js:145:11\n    at file:///home/vicmca/CodeProjects/School/materiais/atividades/3c-rev-01/node_modules/@vitest/runner/dist/index.js:915:26\n    at file:///home/vicmca/CodeProjects/School/materiais/atividades/3c-rev-01/node_modules/@vitest/runner/dist/index.js:1243:20\n    at new Promise (<anonymous>)\n    at runWithTimeout (file:///home/vicmca/CodeProjects/School/materiais/atividades/3c-rev-01/node_modules/@vitest/runner/dist/index.js:1209:10)\n    at file:///home/vicmca/CodeProjects/School/materiais/atividades/3c-rev-01/node_modules/@vitest/runner/dist/index.js:1653:37\n    at Traces.$ (file:///home/vicmca/CodeProjects/School/materiais/atividades/3c-rev-01/node_modules/vitest/dist/chunks/traces.CCmnQaNT.js:142:27)\n    at trace (file:///home/vicmca/CodeProjects/School/materiais/atividades/3c-rev-01/node_modules/vitest/dist/chunks/test.B8ej_ZHS.js:239:21)\n    at runTest (file:///home/vicmca/CodeProjects/School/materiais/atividades/3c-rev-01/node_modules/@vitest/runner/dist/index.js:1653:12)"],"meta":{}},{"ancestorTitles":["Exercício 02"],"fullName":"Exercício 02 Ex02 - Correta - Questão 17","status":"passed","title":"Ex02 - Correta - Questão 17","duration":0.321713999999929,"failureMessages":[],"meta":{}},{"ancestorTitles":["Exercício 02"],"fullName":"Exercício 02 Ex02 - Válida - Questão 18","status":"failed","title":"Ex02 - Válida - Questão 18","duration":1.2901580000000195,"failureMessages":["AssertionError: expected undefined to be type of 'boolean'\n    at /home/vicmca/CodeProjects/School/materiais/atividades/3c-rev-01/exercicios.test.js:60:30\n    at file:///home/vicmca/CodeProjects/School/materiais/atividades/3c-rev-01/node_modules/@vitest/runner/dist/index.js:145:11\n    at file:///home/vicmca/CodeProjects/School/materiais/atividades/3c-rev-01/node_modules/@vitest/runner/dist/index.js:915:26\n    at file:///home/vicmca/CodeProjects/School/materiais/atividades/3c-rev-01/node_modules/@vitest/runner/dist/index.js:1243:20\n    at new Promise (<anonymous>)\n    at runWithTimeout (file:///home/vicmca/CodeProjects/School/materiais/atividades/3c-rev-01/node_modules/@vitest/runner/dist/index.js:1209:10)\n    at file:///home/vicmca/CodeProjects/School/materiais/atividades/3c-rev-01/node_modules/@vitest/runner/dist/index.js:1653:37\n    at Traces.$ (file:///home/vicmca/CodeProjects/School/materiais/atividades/3c-rev-01/node_modules/vitest/dist/chunks/traces.CCmnQaNT.js:142:27)\n    at trace (file:///home/vicmca/CodeProjects/School/materiais/atividades/3c-rev-01/node_modules/vitest/dist/chunks/test.B8ej_ZHS.js:239:21)\n    at runTest (file:///home/vicmca/CodeProjects/School/materiais/atividades/3c-rev-01/node_modules/@vitest/runner/dist/index.js:1653:12)"],"meta":{}},{"ancestorTitles":["Exercício 02"],"fullName":"Exercício 02 Ex02 - Correta - Questão 18","status":"passed","title":"Ex02 - Correta - Questão 18","duration":0.22636499999998705,"failureMessages":[],"meta":{}},{"ancestorTitles":["Exercício 02"],"fullName":"Exercício 02 Ex02 - Válida - Questão 19","status":"failed","title":"Ex02 - Válida - Questão 19","duration":1.2653900000000249,"failureMessages":["AssertionError: expected undefined to be type of 'object'\n    at /home/vicmca/CodeProjects/School/materiais/atividades/3c-rev-01/exercicios.test.js:60:30\n    at file:///home/vicmca/CodeProjects/School/materiais/atividades/3c-rev-01/node_modules/@vitest/runner/dist/index.js:145:11\n    at file:///home/vicmca/CodeProjects/School/materiais/atividades/3c-rev-01/node_modules/@vitest/runner/dist/index.js:915:26\n    at file:///home/vicmca/CodeProjects/School/materiais/atividades/3c-rev-01/node_modules/@vitest/runner/dist/index.js:1243:20\n    at new Promise (<anonymous>)\n    at runWithTimeout (file:///home/vicmca/CodeProjects/School/materiais/atividades/3c-rev-01/node_modules/@vitest/runner/dist/index.js:1209:10)\n    at file:///home/vicmca/CodeProjects/School/materiais/atividades/3c-rev-01/node_modules/@vitest/runner/dist/index.js:1653:37\n    at Traces.$ (file:///home/vicmca/CodeProjects/School/materiais/atividades/3c-rev-01/node_modules/vitest/dist/chunks/traces.CCmnQaNT.js:142:27)\n    at trace (file:///home/vicmca/CodeProjects/School/materiais/atividades/3c-rev-01/node_modules/vitest/dist/chunks/test.B8ej_ZHS.js:239:21)\n    at runTest (file:///home/vicmca/CodeProjects/School/materiais/atividades/3c-rev-01/node_modules/@vitest/runner/dist/index.js:1653:12)"],"meta":{}},{"ancestorTitles":["Exercício 02"],"fullName":"Exercício 02 Ex02 - Correta - Questão 19","status":"passed","title":"Ex02 - Correta - Questão 19","duration":0.2512940000000299,"failureMessages":[],"meta":{}},{"ancestorTitles":["Exercício 02"],"fullName":"Exercício 02 Ex02 - Válida - Questão 20","status":"failed","title":"Ex02 - Válida - Questão 20","duration":1.312187999999992,"failureMessages":["AssertionError: expected undefined to be type of 'boolean'\n    at /home/vicmca/CodeProjects/School/materiais/atividades/3c-rev-01/exercicios.test.js:60:30\n    at file:///home/vicmca/CodeProjects/School/materiais/atividades/3c-rev-01/node_modules/@vitest/runner/dist/index.js:145:11\n    at file:///home/vicmca/CodeProjects/School/materiais/atividades/3c-rev-01/node_modules/@vitest/runner/dist/index.js:915:26\n    at file:///home/vicmca/CodeProjects/School/materiais/atividades/3c-rev-01/node_modules/@vitest/runner/dist/index.js:1243:20\n    at new Promise (<anonymous>)\n    at runWithTimeout (file:///home/vicmca/CodeProjects/School/materiais/atividades/3c-rev-01/node_modules/@vitest/runner/dist/index.js:1209:10)\n    at file:///home/vicmca/CodeProjects/School/materiais/atividades/3c-rev-01/node_modules/@vitest/runner/dist/index.js:1653:37\n    at Traces.$ (file:///home/vicmca/CodeProjects/School/materiais/atividades/3c-rev-01/node_modules/vitest/dist/chunks/traces.CCmnQaNT.js:142:27)\n    at trace (file:///home/vicmca/CodeProjects/School/materiais/atividades/3c-rev-01/node_modules/vitest/dist/chunks/test.B8ej_ZHS.js:239:21)\n    at runTest (file:///home/vicmca/CodeProjects/School/materiais/atividades/3c-rev-01/node_modules/@vitest/runner/dist/index.js:1653:12)"],"meta":{}},{"ancestorTitles":["Exercício 02"],"fullName":"Exercício 02 Ex02 - Correta - Questão 20","status":"passed","title":"Ex02 - Correta - Questão 20","duration":0.19492300000001705,"failureMessages":[],"meta":{}},{"ancestorTitles":["Exercício 03"],"fullName":"Exercício 03 ex03 - Válida - Questão 1","status":"passed","title":"ex03 - Válida - Questão 1","duration":0.41481100000009974,"failureMessages":[],"meta":{}},{"ancestorTitles":["Exercício 03"],"fullName":"Exercício 03 ex03 - Correta - Questão 1","status":"passed","title":"ex03 - Correta - Questão 1","duration":0.29656899999997677,"failureMessages":[],"meta":{}},{"ancestorTitles":["Exercício 03"],"fullName":"Exercício 03 ex03 - Válida - Questão 2","status":"passed","title":"ex03 - Válida - Questão 2","duration":0.24671999999998206,"failureMessages":[],"meta":{}},{"ancestorTitles":["Exercício 03"],"fullName":"Exercício 03 ex03 - Correta - Questão 2","status":"passed","title":"ex03 - Correta - Questão 2","duration":0.12341999999989639,"failureMessages":[],"meta":{}},{"ancestorTitles":["Exercício 03"],"fullName":"Exercício 03 ex03 - Válida - Questão 3","status":"passed","title":"ex03 - Válida - Questão 3","duration":0.17742599999996855,"failureMessages":[],"meta":{}},{"ancestorTitles":["Exercício 03"],"fullName":"Exercício 03 ex03 - Correta - Questão 3","status":"passed","title":"ex03 - Correta - Questão 3","duration":0.19402999999999793,"failureMessages":[],"meta":{}},{"ancestorTitles":["Exercício 03"],"fullName":"Exercício 03 ex03 - Válida - Questão 4","status":"passed","title":"ex03 - Válida - Questão 4","duration":0.38265100000000984,"failureMessages":[],"meta":{}},{"ancestorTitles":["Exercício 03"],"fullName":"Exercício 03 ex03 - Correta - Questão 4","status":"passed","title":"ex03 - Correta - Questão 4","duration":0.166370000000029,"failureMessages":[],"meta":{}},{"ancestorTitles":["Exercício 03"],"fullName":"Exercício 03 ex03 - Válida - Questão 5","status":"passed","title":"ex03 - Válida - Questão 5","duration":0.25505600000008144,"failureMessages":[],"meta":{}},{"ancestorTitles":["Exercício 03"],"fullName":"Exercício 03 ex03 - Correta - Questão 5","status":"passed","title":"ex03 - Correta - Questão 5","duration":0.19153300000004947,"failureMessages":[],"meta":{}},{"ancestorTitles":["Exercício 03"],"fullName":"Exercício 03 ex03 - Válida - Questão 6","status":"passed","title":"ex03 - Válida - Questão 6","duration":0.36487899999997353,"failureMessages":[],"meta":{}},{"ancestorTitles":["Exercício 03"],"fullName":"Exercício 03 ex03 - Correta - Questão 6","status":"passed","title":"ex03 - Correta - Questão 6","duration":0.24098700000001827,"failureMessages":[],"meta":{}},{"ancestorTitles":["Exercício 03"],"fullName":"Exercício 03 ex03 - Válida - Questão 7","status":"failed","title":"ex03 - Válida - Questão 7","duration":3.554890999999998,"failureMessages":["AssertionError: expected undefined to be type of 'boolean'\n    at /home/vicmca/CodeProjects/School/materiais/atividades/3c-rev-01/exercicios.test.js:86:30\n    at file:///home/vicmca/CodeProjects/School/materiais/atividades/3c-rev-01/node_modules/@vitest/runner/dist/index.js:145:11\n    at file:///home/vicmca/CodeProjects/School/materiais/atividades/3c-rev-01/node_modules/@vitest/runner/dist/index.js:915:26\n    at file:///home/vicmca/CodeProjects/School/materiais/atividades/3c-rev-01/node_modules/@vitest/runner/dist/index.js:1243:20\n    at new Promise (<anonymous>)\n    at runWithTimeout (file:///home/vicmca/CodeProjects/School/materiais/atividades/3c-rev-01/node_modules/@vitest/runner/dist/index.js:1209:10)\n    at file:///home/vicmca/CodeProjects/School/materiais/atividades/3c-rev-01/node_modules/@vitest/runner/dist/index.js:1653:37\n    at Traces.$ (file:///home/vicmca/CodeProjects/School/materiais/atividades/3c-rev-01/node_modules/vitest/dist/chunks/traces.CCmnQaNT.js:142:27)\n    at trace (file:///home/vicmca/CodeProjects/School/materiais/atividades/3c-rev-01/node_modules/vitest/dist/chunks/test.B8ej_ZHS.js:239:21)\n    at runTest (file:///home/vicmca/CodeProjects/School/materiais/atividades/3c-rev-01/node_modules/@vitest/runner/dist/index.js:1653:12)"],"meta":{}},{"ancestorTitles":["Exercício 03"],"fullName":"Exercício 03 ex03 - Correta - Questão 7","status":"passed","title":"ex03 - Correta - Questão 7","duration":0.3062439999999924,"failureMessages":[],"meta":{}},{"ancestorTitles":["Exercício 03"],"fullName":"Exercício 03 ex03 - Válida - Questão 8","status":"failed","title":"ex03 - Válida - Questão 8","duration":1.5465699999999742,"failureMessages":["AssertionError: expected undefined to be type of 'boolean'\n    at /home/vicmca/CodeProjects/School/materiais/atividades/3c-rev-01/exercicios.test.js:86:30\n    at file:///home/vicmca/CodeProjects/School/materiais/atividades/3c-rev-01/node_modules/@vitest/runner/dist/index.js:145:11\n    at file:///home/vicmca/CodeProjects/School/materiais/atividades/3c-rev-01/node_modules/@vitest/runner/dist/index.js:915:26\n    at file:///home/vicmca/CodeProjects/School/materiais/atividades/3c-rev-01/node_modules/@vitest/runner/dist/index.js:1243:20\n    at new Promise (<anonymous>)\n    at runWithTimeout (file:///home/vicmca/CodeProjects/School/materiais/atividades/3c-rev-01/node_modules/@vitest/runner/dist/index.js:1209:10)\n    at file:///home/vicmca/CodeProjects/School/materiais/atividades/3c-rev-01/node_modules/@vitest/runner/dist/index.js:1653:37\n    at Traces.$ (file:///home/vicmca/CodeProjects/School/materiais/atividades/3c-rev-01/node_modules/vitest/dist/chunks/traces.CCmnQaNT.js:142:27)\n    at trace (file:///home/vicmca/CodeProjects/School/materiais/atividades/3c-rev-01/node_modules/vitest/dist/chunks/test.B8ej_ZHS.js:239:21)\n    at runTest (file:///home/vicmca/CodeProjects/School/materiais/atividades/3c-rev-01/node_modules/@vitest/runner/dist/index.js:1653:12)"],"meta":{}},{"ancestorTitles":["Exercício 03"],"fullName":"Exercício 03 ex03 - Correta - Questão 8","status":"passed","title":"ex03 - Correta - Questão 8","duration":0.3436970000000201,"failureMessages":[],"meta":{}},{"ancestorTitles":["Exercício 03"],"fullName":"Exercício 03 ex03 - Válida - Questão 9","status":"failed","title":"ex03 - Válida - Questão 9","duration":1.6087489999999889,"failureMessages":["AssertionError: expected undefined to be type of 'boolean'\n    at /home/vicmca/CodeProjects/School/materiais/atividades/3c-rev-01/exercicios.test.js:86:30\n    at file:///home/vicmca/CodeProjects/School/materiais/atividades/3c-rev-01/node_modules/@vitest/runner/dist/index.js:145:11\n    at file:///home/vicmca/CodeProjects/School/materiais/atividades/3c-rev-01/node_modules/@vitest/runner/dist/index.js:915:26\n    at file:///home/vicmca/CodeProjects/School/materiais/atividades/3c-rev-01/node_modules/@vitest/runner/dist/index.js:1243:20\n    at new Promise (<anonymous>)\n    at runWithTimeout (file:///home/vicmca/CodeProjects/School/materiais/atividades/3c-rev-01/node_modules/@vitest/runner/dist/index.js:1209:10)\n    at file:///home/vicmca/CodeProjects/School/materiais/atividades/3c-rev-01/node_modules/@vitest/runner/dist/index.js:1653:37\n    at Traces.$ (file:///home/vicmca/CodeProjects/School/materiais/atividades/3c-rev-01/node_modules/vitest/dist/chunks/traces.CCmnQaNT.js:142:27)\n    at trace (file:///home/vicmca/CodeProjects/School/materiais/atividades/3c-rev-01/node_modules/vitest/dist/chunks/test.B8ej_ZHS.js:239:21)\n    at runTest (file:///home/vicmca/CodeProjects/School/materiais/atividades/3c-rev-01/node_modules/@vitest/runner/dist/index.js:1653:12)"],"meta":{}},{"ancestorTitles":["Exercício 03"],"fullName":"Exercício 03 ex03 - Correta - Questão 9","status":"passed","title":"ex03 - Correta - Questão 9","duration":0.3176449999999704,"failureMessages":[],"meta":{}},{"ancestorTitles":["Exercício 03"],"fullName":"Exercício 03 ex03 - Válida - Questão 10","status":"failed","title":"ex03 - Válida - Questão 10","duration":1.2032070000000203,"failureMessages":["AssertionError: expected undefined to be type of 'boolean'\n    at /home/vicmca/CodeProjects/School/materiais/atividades/3c-rev-01/exercicios.test.js:86:30\n    at file:///home/vicmca/CodeProjects/School/materiais/atividades/3c-rev-01/node_modules/@vitest/runner/dist/index.js:145:11\n    at file:///home/vicmca/CodeProjects/School/materiais/atividades/3c-rev-01/node_modules/@vitest/runner/dist/index.js:915:26\n    at file:///home/vicmca/CodeProjects/School/materiais/atividades/3c-rev-01/node_modules/@vitest/runner/dist/index.js:1243:20\n    at new Promise (<anonymous>)\n    at runWithTimeout (file:///home/vicmca/CodeProjects/School/materiais/atividades/3c-rev-01/node_modules/@vitest/runner/dist/index.js:1209:10)\n    at file:///home/vicmca/CodeProjects/School/materiais/atividades/3c-rev-01/node_modules/@vitest/runner/dist/index.js:1653:37\n    at Traces.$ (file:///home/vicmca/CodeProjects/School/materiais/atividades/3c-rev-01/node_modules/vitest/dist/chunks/traces.CCmnQaNT.js:142:27)\n    at trace (file:///home/vicmca/CodeProjects/School/materiais/atividades/3c-rev-01/node_modules/vitest/dist/chunks/test.B8ej_ZHS.js:239:21)\n    at runTest (file:///home/vicmca/CodeProjects/School/materiais/atividades/3c-rev-01/node_modules/@vitest/runner/dist/index.js:1653:12)"],"meta":{}},{"ancestorTitles":["Exercício 03"],"fullName":"Exercício 03 ex03 - Correta - Questão 10","status":"passed","title":"ex03 - Correta - Questão 10","duration":0.26385399999992387,"failureMessages":[],"meta":{}},{"ancestorTitles":["Exercício 04"],"fullName":"Exercício 04 ex04 - Válida - Questão 1","status":"passed","title":"ex04 - Válida - Questão 1","duration":0.45341900000005353,"failureMessages":[],"meta":{}},{"ancestorTitles":["Exercício 04"],"fullName":"Exercício 04 ex04 - Correta - Questão 1","status":"passed","title":"ex04 - Correta - Questão 1","duration":0.23454499999991185,"failureMessages":[],"meta":{}},{"ancestorTitles":["Exercício 04"],"fullName":"Exercício 04 ex04 - Válida - Questão 2","status":"passed","title":"ex04 - Válida - Questão 2","duration":0.202111000000059,"failureMessages":[],"meta":{}},{"ancestorTitles":["Exercício 04"],"fullName":"Exercício 04 ex04 - Correta - Questão 2","status":"passed","title":"ex04 - Correta - Questão 2","duration":0.13023899999996047,"failureMessages":[],"meta":{}},{"ancestorTitles":["Exercício 04"],"fullName":"Exercício 04 ex04 - Válida - Questão 3","status":"passed","title":"ex04 - Válida - Questão 3","duration":0.19471199999998134,"failureMessages":[],"meta":{}},{"ancestorTitles":["Exercício 04"],"fullName":"Exercício 04 ex04 - Correta - Questão 3","status":"passed","title":"ex04 - Correta - Questão 3","duration":0.12264800000002651,"failureMessages":[],"meta":{}},{"ancestorTitles":["Exercício 04"],"fullName":"Exercício 04 ex04 - Válida - Questão 4","status":"passed","title":"ex04 - Válida - Questão 4","duration":0.19238399999994726,"failureMessages":[],"meta":{}},{"ancestorTitles":["Exercício 04"],"fullName":"Exercício 04 ex04 - Correta - Questão 4","status":"passed","title":"ex04 - Correta - Questão 4","duration":0.12256600000000617,"failureMessages":[],"meta":{}},{"ancestorTitles":["Exercício 04"],"fullName":"Exercício 04 ex04 - Válida - Questão 5","status":"passed","title":"ex04 - Válida - Questão 5","duration":0.17799400000001242,"failureMessages":[],"meta":{}},{"ancestorTitles":["Exercício 04"],"fullName":"Exercício 04 ex04 - Correta - Questão 5","status":"passed","title":"ex04 - Correta - Questão 5","duration":0.1158300000000736,"failureMessages":[],"meta":{}},{"ancestorTitles":["Exercício 04"],"fullName":"Exercício 04 ex04 - Válida - Questão 6","status":"passed","title":"ex04 - Válida - Questão 6","duration":0.17694700000004104,"failureMessages":[],"meta":{}},{"ancestorTitles":["Exercício 04"],"fullName":"Exercício 04 ex04 - Correta - Questão 6","status":"passed","title":"ex04 - Correta - Questão 6","duration":0.2524029999999584,"failureMessages":[],"meta":{}},{"ancestorTitles":["Exercício 04"],"fullName":"Exercício 04 ex04 - Válida - Questão 7","status":"passed","title":"ex04 - Válida - Questão 7","duration":0.27435700000000907,"failureMessages":[],"meta":{}},{"ancestorTitles":["Exercício 04"],"fullName":"Exercício 04 ex04 - Correta - Questão 7","status":"passed","title":"ex04 - Correta - Questão 7","duration":0.19977300000005016,"failureMessages":[],"meta":{}},{"ancestorTitles":["Exercício 04"],"fullName":"Exercício 04 ex04 - Válida - Questão 8","status":"passed","title":"ex04 - Válida - Questão 8","duration":0.28829099999995833,"failureMessages":[],"meta":{}},{"ancestorTitles":["Exercício 04"],"fullName":"Exercício 04 ex04 - Correta - Questão 8","status":"passed","title":"ex04 - Correta - Questão 8","duration":0.23599500000000262,"failureMessages":[],"meta":{}},{"ancestorTitles":["Exercício 04"],"fullName":"Exercício 04 ex04 - Válida - Questão 9","status":"passed","title":"ex04 - Válida - Questão 9","duration":0.3097050000000081,"failureMessages":[],"meta":{}},{"ancestorTitles":["Exercício 04"],"fullName":"Exercício 04 ex04 - Correta - Questão 9","status":"passed","title":"ex04 - Correta - Questão 9","duration":0.2126140000000305,"failureMessages":[],"meta":{}},{"ancestorTitles":["Exercício 04"],"fullName":"Exercício 04 ex04 - Válida - Questão 10","status":"passed","title":"ex04 - Válida - Questão 10","duration":0.29288499999995565,"failureMessages":[],"meta":{}},{"ancestorTitles":["Exercício 04"],"fullName":"Exercício 04 ex04 - Correta - Questão 10","status":"passed","title":"ex04 - Correta - Questão 10","duration":0.2273369999999204,"failureMessages":[],"meta":{}},{"ancestorTitles":["Exercício 04"],"fullName":"Exercício 04 ex04 - Válida - Questão 11","status":"passed","title":"ex04 - Válida - Questão 11","duration":0.28395100000000184,"failureMessages":[],"meta":{}},{"ancestorTitles":["Exercício 04"],"fullName":"Exercício 04 ex04 - Correta - Questão 11","status":"passed","title":"ex04 - Correta - Questão 11","duration":0.29308800000001156,"failureMessages":[],"meta":{}},{"ancestorTitles":["Exercício 04"],"fullName":"Exercício 04 ex04 - Válida - Questão 12","status":"passed","title":"ex04 - Válida - Questão 12","duration":0.2998450000000048,"failureMessages":[],"meta":{}},{"ancestorTitles":["Exercício 04"],"fullName":"Exercício 04 ex04 - Correta - Questão 12","status":"passed","title":"ex04 - Correta - Questão 12","duration":0.32222600000000057,"failureMessages":[],"meta":{}},{"ancestorTitles":["Exercício 04"],"fullName":"Exercício 04 ex04 - Válida - Questão 13","status":"passed","title":"ex04 - Válida - Questão 13","duration":0.22312599999997929,"failureMessages":[],"meta":{}},{"ancestorTitles":["Exercício 04"],"fullName":"Exercício 04 ex04 - Correta - Questão 13","status":"passed","title":"ex04 - Correta - Questão 13","duration":0.12651000000005297,"failureMessages":[],"meta":{}},{"ancestorTitles":["Exercício 04"],"fullName":"Exercício 04 ex04 - Válida - Questão 14","status":"passed","title":"ex04 - Válida - Questão 14","duration":0.17862800000000334,"failureMessages":[],"meta":{}},{"ancestorTitles":["Exercício 04"],"fullName":"Exercício 04 ex04 - Correta - Questão 14","status":"passed","title":"ex04 - Correta - Questão 14","duration":0.12056000000006861,"failureMessages":[],"meta":{}},{"ancestorTitles":["Exercício 04"],"fullName":"Exercício 04 ex04 - Válida - Questão 15","status":"passed","title":"ex04 - Válida - Questão 15","duration":0.18380200000001423,"failureMessages":[],"meta":{}},{"ancestorTitles":["Exercício 04"],"fullName":"Exercício 04 ex04 - Correta - Questão 15","status":"passed","title":"ex04 - Correta - Questão 15","duration":0.11898599999994985,"failureMessages":[],"meta":{}},{"ancestorTitles":["Exercício 04"],"fullName":"Exercício 04 ex04 - Válida - Questão 16","status":"passed","title":"ex04 - Válida - Questão 16","duration":0.20036100000004353,"failureMessages":[],"meta":{}},{"ancestorTitles":["Exercício 04"],"fullName":"Exercício 04 ex04 - Correta - Questão 16","status":"passed","title":"ex04 - Correta - Questão 16","duration":0.1559780000000046,"failureMessages":[],"meta":{}},{"ancestorTitles":["Exercício 04"],"fullName":"Exercício 04 ex04 - Válida - Questão 17","status":"passed","title":"ex04 - Válida - Questão 17","duration":0.22452399999997397,"failureMessages":[],"meta":{}},{"ancestorTitles":["Exercício 04"],"fullName":"Exercício 04 ex04 - Correta - Questão 17","status":"passed","title":"ex04 - Correta - Questão 17","duration":0.13663200000007691,"failureMessages":[],"meta":{}},{"ancestorTitles":["Exercício 04"],"fullName":"Exercício 04 ex04 - Válida - Questão 18","status":"passed","title":"ex04 - Válida - Questão 18","duration":0.20352700000000823,"failureMessages":[],"meta":{}},{"ancestorTitles":["Exercício 04"],"fullName":"Exercício 04 ex04 - Correta - Questão 18","status":"passed","title":"ex04 - Correta - Questão 18","duration":0.14899500000001353,"failureMessages":[],"meta":{}},{"ancestorTitles":["Exercício 04"],"fullName":"Exercício 04 ex04 - Válida - Questão 19","status":"passed","title":"ex04 - Válida - Questão 19","duration":0.1962700000000268,"failureMessages":[],"meta":{}},{"ancestorTitles":["Exercício 04"],"fullName":"Exercício 04 ex04 - Correta - Questão 19","status":"passed","title":"ex04 - Correta - Questão 19","duration":0.15967200000000048,"failureMessages":[],"meta":{}},{"ancestorTitles":["Exercício 04"],"fullName":"Exercício 04 ex04 - Válida - Questão 20","status":"passed","title":"ex04 - Válida - Questão 20","duration":0.18736699999999473,"failureMessages":[],"meta":{}},{"ancestorTitles":["Exercício 04"],"fullName":"Exercício 04 ex04 - Correta - Questão 20","status":"passed","title":"ex04 - Correta - Questão 20","duration":0.16518599999994876,"failureMessages":[],"meta":{}},{"ancestorTitles":["Exercício 05"],"fullName":"Exercício 05 ex05 - Válida - Questão 1","status":"passed","title":"ex05 - Válida - Questão 1","duration":0.33284600000001774,"failureMessages":[],"meta":{}},{"ancestorTitles":["Exercício 05"],"fullName":"Exercício 05 ex05 - Correta - Questão 1","status":"passed","title":"ex05 - Correta - Questão 1","duration":0.469065999999998,"failureMessages":[],"meta":{}},{"ancestorTitles":["Exercício 05"],"fullName":"Exercício 05 ex05 - Válida - Questão 2","status":"passed","title":"ex05 - Válida - Questão 2","duration":0.2372299999999541,"failureMessages":[],"meta":{}},{"ancestorTitles":["Exercício 05"],"fullName":"Exercício 05 ex05 - Correta - Questão 2","status":"passed","title":"ex05 - Correta - Questão 2","duration":0.16439500000001317,"failureMessages":[],"meta":{}},{"ancestorTitles":["Exercício 05"],"fullName":"Exercício 05 ex05 - Válida - Questão 3","status":"passed","title":"ex05 - Válida - Questão 3","duration":0.2868319999998903,"failureMessages":[],"meta":{}},{"ancestorTitles":["Exercício 05"],"fullName":"Exercício 05 ex05 - Correta - Questão 3","status":"passed","title":"ex05 - Correta - Questão 3","duration":0.16911700000002838,"failureMessages":[],"meta":{}},{"ancestorTitles":["Exercício 05"],"fullName":"Exercício 05 ex05 - Válida - Questão 4","status":"passed","title":"ex05 - Válida - Questão 4","duration":0.19552199999998265,"failureMessages":[],"meta":{}},{"ancestorTitles":["Exercício 05"],"fullName":"Exercício 05 ex05 - Correta - Questão 4","status":"passed","title":"ex05 - Correta - Questão 4","duration":0.15338200000007873,"failureMessages":[],"meta":{}},{"ancestorTitles":["Exercício 05"],"fullName":"Exercício 05 ex05 - Válida - Questão 5","status":"passed","title":"ex05 - Válida - Questão 5","duration":0.29872100000000046,"failureMessages":[],"meta":{}},{"ancestorTitles":["Exercício 05"],"fullName":"Exercício 05 ex05 - Correta - Questão 5","status":"passed","title":"ex05 - Correta - Questão 5","duration":0.16008899999997084,"failureMessages":[],"meta":{}},{"ancestorTitles":["Exercício 05"],"fullName":"Exercício 05 ex05 - Válida - Questão 6","status":"passed","title":"ex05 - Válida - Questão 6","duration":0.18599199999994198,"failureMessages":[],"meta":{}},{"ancestorTitles":["Exercício 05"],"fullName":"Exercício 05 ex05 - Correta - Questão 6","status":"passed","title":"ex05 - Correta - Questão 6","duration":0.1607289999999466,"failureMessages":[],"meta":{}},{"ancestorTitles":["Exercício 05"],"fullName":"Exercício 05 ex05 - Válida - Questão 7","status":"passed","title":"ex05 - Válida - Questão 7","duration":0.2695979999999736,"failureMessages":[],"meta":{}},{"ancestorTitles":["Exercício 05"],"fullName":"Exercício 05 ex05 - Correta - Questão 7","status":"passed","title":"ex05 - Correta - Questão 7","duration":0.17819599999995717,"failureMessages":[],"meta":{}},{"ancestorTitles":["Exercício 05"],"fullName":"Exercício 05 ex05 - Válida - Questão 8","status":"passed","title":"ex05 - Válida - Questão 8","duration":0.23364900000001398,"failureMessages":[],"meta":{}},{"ancestorTitles":["Exercício 05"],"fullName":"Exercício 05 ex05 - Correta - Questão 8","status":"passed","title":"ex05 - Correta - Questão 8","duration":0.2895849999999882,"failureMessages":[],"meta":{}},{"ancestorTitles":["Exercício 05"],"fullName":"Exercício 05 ex05 - Válida - Questão 9","status":"passed","title":"ex05 - Válida - Questão 9","duration":0.2277440000000297,"failureMessages":[],"meta":{}},{"ancestorTitles":["Exercício 05"],"fullName":"Exercício 05 ex05 - Correta - Questão 9","status":"passed","title":"ex05 - Correta - Questão 9","duration":0.16129399999999805,"failureMessages":[],"meta":{}},{"ancestorTitles":["Exercício 05"],"fullName":"Exercício 05 ex05 - Válida - Questão 10","status":"passed","title":"ex05 - Válida - Questão 10","duration":0.25678499999992255,"failureMessages":[],"meta":{}},{"ancestorTitles":["Exercício 05"],"fullName":"Exercício 05 ex05 - Correta - Questão 10","status":"passed","title":"ex05 - Correta - Questão 10","duration":0.30401900000003934,"failureMessages":[],"meta":{}}],"startTime":1773057518858,"endTime":1773057518985.304,"status":"failed","message":"","name":"/home/vicmca/CodeProjects/School/materiais/atividades/3c-rev-01/exercicios.test.js"}]}