{"numTotalTestSuites":6,"numPassedTestSuites":4,"numFailedTestSuites":2,"numPendingTestSuites":0,"numTotalTests":160,"numPassedTests":154,"numFailedTests":6,"numPendingTests":0,"numTodoTests":0,"snapshot":{"added":0,"failure":false,"filesAdded":0,"filesRemoved":0,"filesRemovedList":[],"filesUnmatched":0,"filesUpdated":0,"matched":0,"total":0,"unchecked":0,"uncheckedKeysByFile":[],"unmatched":0,"updated":0,"didUpdate":false},"startTime":1773057413476,"success":false,"testResults":[{"assertionResults":[{"ancestorTitles":["Exercício 01"],"fullName":"Exercício 01 Ex01 - Válida - Questão 1","status":"passed","title":"Ex01 - Válida - Questão 1","duration":7.110752999999988,"failureMessages":[],"meta":{}},{"ancestorTitles":["Exercício 01"],"fullName":"Exercício 01 Ex01 - Correta - Questão 1","status":"passed","title":"Ex01 - Correta - Questão 1","duration":1.0459210000000212,"failureMessages":[],"meta":{}},{"ancestorTitles":["Exercício 01"],"fullName":"Exercício 01 Ex01 - Válida - Questão 2","status":"passed","title":"Ex01 - Válida - Questão 2","duration":0.6220419999999649,"failureMessages":[],"meta":{}},{"ancestorTitles":["Exercício 01"],"fullName":"Exercício 01 Ex01 - Correta - Questão 2","status":"passed","title":"Ex01 - Correta - Questão 2","duration":1.0705629999999928,"failureMessages":[],"meta":{}},{"ancestorTitles":["Exercício 01"],"fullName":"Exercício 01 Ex01 - Válida - Questão 3","status":"passed","title":"Ex01 - Válida - Questão 3","duration":0.6359709999999836,"failureMessages":[],"meta":{}},{"ancestorTitles":["Exercício 01"],"fullName":"Exercício 01 Ex01 - Correta - Questão 3","status":"passed","title":"Ex01 - Correta - Questão 3","duration":0.7538059999999973,"failureMessages":[],"meta":{}},{"ancestorTitles":["Exercício 01"],"fullName":"Exercício 01 Ex01 - Válida - Questão 4","status":"failed","title":"Ex01 - Válida - Questão 4","duration":29.72272499999997,"failureMessages":["AssertionError: expected undefined to be type of 'boolean'\n    at /home/vicmca/CodeProjects/School/materiais/atividades/3c-rev-01/exercicios.test.js:28:30\n    at file:///home/vicmca/CodeProjects/School/materiais/atividades/3c-rev-01/node_modules/@vitest/runner/dist/index.js:145:11\n    at file:///home/vicmca/CodeProjects/School/materiais/atividades/3c-rev-01/node_modules/@vitest/runner/dist/index.js:915:26\n    at file:///home/vicmca/CodeProjects/School/materiais/atividades/3c-rev-01/node_modules/@vitest/runner/dist/index.js:1243:20\n    at new Promise (<anonymous>)\n    at runWithTimeout (file:///home/vicmca/CodeProjects/School/materiais/atividades/3c-rev-01/node_modules/@vitest/runner/dist/index.js:1209:10)\n    at file:///home/vicmca/CodeProjects/School/materiais/atividades/3c-rev-01/node_modules/@vitest/runner/dist/index.js:1653:37\n    at Traces.$ (file:///home/vicmca/CodeProjects/School/materiais/atividades/3c-rev-01/node_modules/vitest/dist/chunks/traces.CCmnQaNT.js:142:27)\n    at trace (file:///home/vicmca/CodeProjects/School/materiais/atividades/3c-rev-01/node_modules/vitest/dist/chunks/test.B8ej_ZHS.js:239:21)\n    at runTest (file:///home/vicmca/CodeProjects/School/materiais/atividades/3c-rev-01/node_modules/@vitest/runner/dist/index.js:1653:12)"],"meta":{}},{"ancestorTitles":["Exercício 01"],"fullName":"Exercício 01 Ex01 - Correta - Questão 4","status":"failed","title":"Ex01 - Correta - Questão 4","duration":8.429156000000035,"failureMessages":["AssertionError: expected undefined to be type of 'boolean'\n    at /home/vicmca/CodeProjects/School/materiais/atividades/3c-rev-01/exercicios.test.js:32:30\n    at file:///home/vicmca/CodeProjects/School/materiais/atividades/3c-rev-01/node_modules/@vitest/runner/dist/index.js:145:11\n    at file:///home/vicmca/CodeProjects/School/materiais/atividades/3c-rev-01/node_modules/@vitest/runner/dist/index.js:915:26\n    at file:///home/vicmca/CodeProjects/School/materiais/atividades/3c-rev-01/node_modules/@vitest/runner/dist/index.js:1243:20\n    at new Promise (<anonymous>)\n    at runWithTimeout (file:///home/vicmca/CodeProjects/School/materiais/atividades/3c-rev-01/node_modules/@vitest/runner/dist/index.js:1209:10)\n    at file:///home/vicmca/CodeProjects/School/materiais/atividades/3c-rev-01/node_modules/@vitest/runner/dist/index.js:1653:37\n    at Traces.$ (file:///home/vicmca/CodeProjects/School/materiais/atividades/3c-rev-01/node_modules/vitest/dist/chunks/traces.CCmnQaNT.js:142:27)\n    at trace (file:///home/vicmca/CodeProjects/School/materiais/atividades/3c-rev-01/node_modules/vitest/dist/chunks/test.B8ej_ZHS.js:239:21)\n    at runTest (file:///home/vicmca/CodeProjects/School/materiais/atividades/3c-rev-01/node_modules/@vitest/runner/dist/index.js:1653:12)"],"meta":{}},{"ancestorTitles":["Exercício 01"],"fullName":"Exercício 01 Ex01 - Válida - Questão 5","status":"passed","title":"Ex01 - Válida - Questão 5","duration":1.02740799999998,"failureMessages":[],"meta":{}},{"ancestorTitles":["Exercício 01"],"fullName":"Exercício 01 Ex01 - Correta - Questão 5","status":"passed","title":"Ex01 - Correta - Questão 5","duration":0.3865470000000073,"failureMessages":[],"meta":{}},{"ancestorTitles":["Exercício 01"],"fullName":"Exercício 01 Ex01 - Válida - Questão 6","status":"passed","title":"Ex01 - Válida - Questão 6","duration":0.41427599999997256,"failureMessages":[],"meta":{}},{"ancestorTitles":["Exercício 01"],"fullName":"Exercício 01 Ex01 - Correta - Questão 6","status":"passed","title":"Ex01 - Correta - Questão 6","duration":0.26087400000000116,"failureMessages":[],"meta":{}},{"ancestorTitles":["Exercício 01"],"fullName":"Exercício 01 Ex01 - Válida - Questão 7","status":"passed","title":"Ex01 - Válida - Questão 7","duration":0.3106430000000273,"failureMessages":[],"meta":{}},{"ancestorTitles":["Exercício 01"],"fullName":"Exercício 01 Ex01 - Correta - Questão 7","status":"passed","title":"Ex01 - Correta - Questão 7","duration":0.16071300000004385,"failureMessages":[],"meta":{}},{"ancestorTitles":["Exercício 01"],"fullName":"Exercício 01 Ex01 - Válida - Questão 8","status":"passed","title":"Ex01 - Válida - Questão 8","duration":0.21056200000003855,"failureMessages":[],"meta":{}},{"ancestorTitles":["Exercício 01"],"fullName":"Exercício 01 Ex01 - Correta - Questão 8","status":"passed","title":"Ex01 - Correta - Questão 8","duration":0.1471339999999941,"failureMessages":[],"meta":{}},{"ancestorTitles":["Exercício 01"],"fullName":"Exercício 01 Ex01 - Válida - Questão 9","status":"failed","title":"Ex01 - Válida - Questão 9","duration":2.2082450000000335,"failureMessages":["AssertionError: expected undefined to be type of 'boolean'\n    at /home/vicmca/CodeProjects/School/materiais/atividades/3c-rev-01/exercicios.test.js:28:30\n    at file:///home/vicmca/CodeProjects/School/materiais/atividades/3c-rev-01/node_modules/@vitest/runner/dist/index.js:145:11\n    at file:///home/vicmca/CodeProjects/School/materiais/atividades/3c-rev-01/node_modules/@vitest/runner/dist/index.js:915:26\n    at file:///home/vicmca/CodeProjects/School/materiais/atividades/3c-rev-01/node_modules/@vitest/runner/dist/index.js:1243:20\n    at new Promise (<anonymous>)\n    at runWithTimeout (file:///home/vicmca/CodeProjects/School/materiais/atividades/3c-rev-01/node_modules/@vitest/runner/dist/index.js:1209:10)\n    at file:///home/vicmca/CodeProjects/School/materiais/atividades/3c-rev-01/node_modules/@vitest/runner/dist/index.js:1653:37\n    at Traces.$ (file:///home/vicmca/CodeProjects/School/materiais/atividades/3c-rev-01/node_modules/vitest/dist/chunks/traces.CCmnQaNT.js:142:27)\n    at trace (file:///home/vicmca/CodeProjects/School/materiais/atividades/3c-rev-01/node_modules/vitest/dist/chunks/test.B8ej_ZHS.js:239:21)\n    at runTest (file:///home/vicmca/CodeProjects/School/materiais/atividades/3c-rev-01/node_modules/@vitest/runner/dist/index.js:1653:12)"],"meta":{}},{"ancestorTitles":["Exercício 01"],"fullName":"Exercício 01 Ex01 - Correta - Questão 9","status":"failed","title":"Ex01 - Correta - Questão 9","duration":1.588575999999989,"failureMessages":["AssertionError: expected undefined to be type of 'boolean'\n    at /home/vicmca/CodeProjects/School/materiais/atividades/3c-rev-01/exercicios.test.js:32:30\n    at file:///home/vicmca/CodeProjects/School/materiais/atividades/3c-rev-01/node_modules/@vitest/runner/dist/index.js:145:11\n    at file:///home/vicmca/CodeProjects/School/materiais/atividades/3c-rev-01/node_modules/@vitest/runner/dist/index.js:915:26\n    at file:///home/vicmca/CodeProjects/School/materiais/atividades/3c-rev-01/node_modules/@vitest/runner/dist/index.js:1243:20\n    at new Promise (<anonymous>)\n    at runWithTimeout (file:///home/vicmca/CodeProjects/School/materiais/atividades/3c-rev-01/node_modules/@vitest/runner/dist/index.js:1209:10)\n    at file:///home/vicmca/CodeProjects/School/materiais/atividades/3c-rev-01/node_modules/@vitest/runner/dist/index.js:1653:37\n    at Traces.$ (file:///home/vicmca/CodeProjects/School/materiais/atividades/3c-rev-01/node_modules/vitest/dist/chunks/traces.CCmnQaNT.js:142:27)\n    at trace (file:///home/vicmca/CodeProjects/School/materiais/atividades/3c-rev-01/node_modules/vitest/dist/chunks/test.B8ej_ZHS.js:239:21)\n    at runTest (file:///home/vicmca/CodeProjects/School/materiais/atividades/3c-rev-01/node_modules/@vitest/runner/dist/index.js:1653:12)"],"meta":{}},{"ancestorTitles":["Exercício 01"],"fullName":"Exercício 01 Ex01 - Válida - Questão 10","status":"passed","title":"Ex01 - Válida - Questão 10","duration":0.4096499999999992,"failureMessages":[],"meta":{}},{"ancestorTitles":["Exercício 01"],"fullName":"Exercício 01 Ex01 - Correta - Questão 10","status":"passed","title":"Ex01 - Correta - Questão 10","duration":0.17294700000002194,"failureMessages":[],"meta":{}},{"ancestorTitles":["Exercício 01"],"fullName":"Exercício 01 Ex01 - Válida - Questão 11","status":"passed","title":"Ex01 - Válida - Questão 11","duration":0.22133600000000797,"failureMessages":[],"meta":{}},{"ancestorTitles":["Exercício 01"],"fullName":"Exercício 01 Ex01 - Correta - Questão 11","status":"passed","title":"Ex01 - Correta - Questão 11","duration":0.15125700000004372,"failureMessages":[],"meta":{}},{"ancestorTitles":["Exercício 01"],"fullName":"Exercício 01 Ex01 - Válida - Questão 12","status":"passed","title":"Ex01 - Válida - Questão 12","duration":0.20876399999997375,"failureMessages":[],"meta":{}},{"ancestorTitles":["Exercício 01"],"fullName":"Exercício 01 Ex01 - Correta - Questão 12","status":"passed","title":"Ex01 - Correta - Questão 12","duration":0.15237800000005564,"failureMessages":[],"meta":{}},{"ancestorTitles":["Exercício 01"],"fullName":"Exercício 01 Ex01 - Válida - Questão 13","status":"passed","title":"Ex01 - Válida - Questão 13","duration":0.23132399999997233,"failureMessages":[],"meta":{}},{"ancestorTitles":["Exercício 01"],"fullName":"Exercício 01 Ex01 - Correta - Questão 13","status":"passed","title":"Ex01 - Correta - Questão 13","duration":0.1999150000000327,"failureMessages":[],"meta":{}},{"ancestorTitles":["Exercício 01"],"fullName":"Exercício 01 Ex01 - Válida - Questão 14","status":"passed","title":"Ex01 - Válida - Questão 14","duration":0.18897299999997585,"failureMessages":[],"meta":{}},{"ancestorTitles":["Exercício 01"],"fullName":"Exercício 01 Ex01 - Correta - Questão 14","status":"passed","title":"Ex01 - Correta - Questão 14","duration":0.13363400000002912,"failureMessages":[],"meta":{}},{"ancestorTitles":["Exercício 01"],"fullName":"Exercício 01 Ex01 - Válida - Questão 15","status":"passed","title":"Ex01 - Válida - Questão 15","duration":0.22220399999997653,"failureMessages":[],"meta":{}},{"ancestorTitles":["Exercício 01"],"fullName":"Exercício 01 Ex01 - Correta - Questão 15","status":"passed","title":"Ex01 - Correta - Questão 15","duration":0.1475849999999923,"failureMessages":[],"meta":{}},{"ancestorTitles":["Exercício 01"],"fullName":"Exercício 01 Ex01 - Válida - Questão 16","status":"passed","title":"Ex01 - Válida - Questão 16","duration":0.1914000000000442,"failureMessages":[],"meta":{}},{"ancestorTitles":["Exercício 01"],"fullName":"Exercício 01 Ex01 - Correta - Questão 16","status":"passed","title":"Ex01 - Correta - Questão 16","duration":0.15356400000001713,"failureMessages":[],"meta":{}},{"ancestorTitles":["Exercício 01"],"fullName":"Exercício 01 Ex01 - Válida - Questão 17","status":"failed","title":"Ex01 - Válida - Questão 17","duration":2.438845000000015,"failureMessages":["AssertionError: expected undefined to be type of 'boolean'\n    at /home/vicmca/CodeProjects/School/materiais/atividades/3c-rev-01/exercicios.test.js:28:30\n    at file:///home/vicmca/CodeProjects/School/materiais/atividades/3c-rev-01/node_modules/@vitest/runner/dist/index.js:145:11\n    at file:///home/vicmca/CodeProjects/School/materiais/atividades/3c-rev-01/node_modules/@vitest/runner/dist/index.js:915:26\n    at file:///home/vicmca/CodeProjects/School/materiais/atividades/3c-rev-01/node_modules/@vitest/runner/dist/index.js:1243:20\n    at new Promise (<anonymous>)\n    at runWithTimeout (file:///home/vicmca/CodeProjects/School/materiais/atividades/3c-rev-01/node_modules/@vitest/runner/dist/index.js:1209:10)\n    at file:///home/vicmca/CodeProjects/School/materiais/atividades/3c-rev-01/node_modules/@vitest/runner/dist/index.js:1653:37\n    at Traces.$ (file:///home/vicmca/CodeProjects/School/materiais/atividades/3c-rev-01/node_modules/vitest/dist/chunks/traces.CCmnQaNT.js:142:27)\n    at trace (file:///home/vicmca/CodeProjects/School/materiais/atividades/3c-rev-01/node_modules/vitest/dist/chunks/test.B8ej_ZHS.js:239:21)\n    at runTest (file:///home/vicmca/CodeProjects/School/materiais/atividades/3c-rev-01/node_modules/@vitest/runner/dist/index.js:1653:12)"],"meta":{}},{"ancestorTitles":["Exercício 01"],"fullName":"Exercício 01 Ex01 - Correta - Questão 17","status":"failed","title":"Ex01 - Correta - Questão 17","duration":1.3460660000000075,"failureMessages":["AssertionError: expected undefined to be type of 'boolean'\n    at /home/vicmca/CodeProjects/School/materiais/atividades/3c-rev-01/exercicios.test.js:32:30\n    at file:///home/vicmca/CodeProjects/School/materiais/atividades/3c-rev-01/node_modules/@vitest/runner/dist/index.js:145:11\n    at file:///home/vicmca/CodeProjects/School/materiais/atividades/3c-rev-01/node_modules/@vitest/runner/dist/index.js:915:26\n    at file:///home/vicmca/CodeProjects/School/materiais/atividades/3c-rev-01/node_modules/@vitest/runner/dist/index.js:1243:20\n    at new Promise (<anonymous>)\n    at runWithTimeout (file:///home/vicmca/CodeProjects/School/materiais/atividades/3c-rev-01/node_modules/@vitest/runner/dist/index.js:1209:10)\n    at file:///home/vicmca/CodeProjects/School/materiais/atividades/3c-rev-01/node_modules/@vitest/runner/dist/index.js:1653:37\n    at Traces.$ (file:///home/vicmca/CodeProjects/School/materiais/atividades/3c-rev-01/node_modules/vitest/dist/chunks/traces.CCmnQaNT.js:142:27)\n    at trace (file:///home/vicmca/CodeProjects/School/materiais/atividades/3c-rev-01/node_modules/vitest/dist/chunks/test.B8ej_ZHS.js:239:21)\n    at runTest (file:///home/vicmca/CodeProjects/School/materiais/atividades/3c-rev-01/node_modules/@vitest/runner/dist/index.js:1653:12)"],"meta":{}},{"ancestorTitles":["Exercício 01"],"fullName":"Exercício 01 Ex01 - Válida - Questão 18","status":"passed","title":"Ex01 - Válida - Questão 18","duration":0.34254800000002206,"failureMessages":[],"meta":{}},{"ancestorTitles":["Exercício 01"],"fullName":"Exercício 01 Ex01 - Correta - Questão 18","status":"passed","title":"Ex01 - Correta - Questão 18","duration":0.19715000000002192,"failureMessages":[],"meta":{}},{"ancestorTitles":["Exercício 01"],"fullName":"Exercício 01 Ex01 - Válida - Questão 19","status":"passed","title":"Ex01 - Válida - Questão 19","duration":0.270657999999969,"failureMessages":[],"meta":{}},{"ancestorTitles":["Exercício 01"],"fullName":"Exercício 01 Ex01 - Correta - Questão 19","status":"passed","title":"Ex01 - Correta - Questão 19","duration":0.177250000000015,"failureMessages":[],"meta":{}},{"ancestorTitles":["Exercício 01"],"fullName":"Exercício 01 Ex01 - Válida - Questão 20","status":"passed","title":"Ex01 - Válida - Questão 20","duration":0.220737999999983,"failureMessages":[],"meta":{}},{"ancestorTitles":["Exercício 01"],"fullName":"Exercício 01 Ex01 - Correta - Questão 20","status":"passed","title":"Ex01 - Correta - Questão 20","duration":0.16214199999990342,"failureMessages":[],"meta":{}},{"ancestorTitles":["Exercício 02"],"fullName":"Exercício 02 Ex02 - Válida - Questão 1","status":"passed","title":"Ex02 - Válida - Questão 1","duration":0.3699229999999716,"failureMessages":[],"meta":{}},{"ancestorTitles":["Exercício 02"],"fullName":"Exercício 02 Ex02 - Correta - Questão 1","status":"passed","title":"Ex02 - Correta - Questão 1","duration":0.23657600000001366,"failureMessages":[],"meta":{}},{"ancestorTitles":["Exercício 02"],"fullName":"Exercício 02 Ex02 - Válida - Questão 2","status":"passed","title":"Ex02 - Válida - Questão 2","duration":0.22709000000008928,"failureMessages":[],"meta":{}},{"ancestorTitles":["Exercício 02"],"fullName":"Exercício 02 Ex02 - Correta - Questão 2","status":"passed","title":"Ex02 - Correta - Questão 2","duration":0.18639600000005885,"failureMessages":[],"meta":{}},{"ancestorTitles":["Exercício 02"],"fullName":"Exercício 02 Ex02 - Válida - Questão 3","status":"passed","title":"Ex02 - Válida - Questão 3","duration":0.2617079999999987,"failureMessages":[],"meta":{}},{"ancestorTitles":["Exercício 02"],"fullName":"Exercício 02 Ex02 - Correta - Questão 3","status":"passed","title":"Ex02 - Correta - Questão 3","duration":0.17036299999995208,"failureMessages":[],"meta":{}},{"ancestorTitles":["Exercício 02"],"fullName":"Exercício 02 Ex02 - Válida - Questão 4","status":"passed","title":"Ex02 - Válida - Questão 4","duration":0.26888000000008105,"failureMessages":[],"meta":{}},{"ancestorTitles":["Exercício 02"],"fullName":"Exercício 02 Ex02 - Correta - Questão 4","status":"passed","title":"Ex02 - Correta - Questão 4","duration":0.12917099999992843,"failureMessages":[],"meta":{}},{"ancestorTitles":["Exercício 02"],"fullName":"Exercício 02 Ex02 - Válida - Questão 5","status":"passed","title":"Ex02 - Válida - Questão 5","duration":0.24224100000003546,"failureMessages":[],"meta":{}},{"ancestorTitles":["Exercício 02"],"fullName":"Exercício 02 Ex02 - Correta - Questão 5","status":"passed","title":"Ex02 - Correta - Questão 5","duration":0.21739999999999782,"failureMessages":[],"meta":{}},{"ancestorTitles":["Exercício 02"],"fullName":"Exercício 02 Ex02 - Válida - Questão 6","status":"passed","title":"Ex02 - Válida - Questão 6","duration":0.22682700000007117,"failureMessages":[],"meta":{}},{"ancestorTitles":["Exercício 02"],"fullName":"Exercício 02 Ex02 - Correta - Questão 6","status":"passed","title":"Ex02 - Correta - Questão 6","duration":0.18928700000003573,"failureMessages":[],"meta":{}},{"ancestorTitles":["Exercício 02"],"fullName":"Exercício 02 Ex02 - Válida - Questão 7","status":"passed","title":"Ex02 - Válida - Questão 7","duration":0.203296000000023,"failureMessages":[],"meta":{}},{"ancestorTitles":["Exercício 02"],"fullName":"Exercício 02 Ex02 - Correta - Questão 7","status":"passed","title":"Ex02 - Correta - Questão 7","duration":0.12332499999990887,"failureMessages":[],"meta":{}},{"ancestorTitles":["Exercício 02"],"fullName":"Exercício 02 Ex02 - Válida - Questão 8","status":"passed","title":"Ex02 - Válida - Questão 8","duration":0.19445599999994556,"failureMessages":[],"meta":{}},{"ancestorTitles":["Exercício 02"],"fullName":"Exercício 02 Ex02 - Correta - Questão 8","status":"passed","title":"Ex02 - Correta - Questão 8","duration":0.11503100000004451,"failureMessages":[],"meta":{}},{"ancestorTitles":["Exercício 02"],"fullName":"Exercício 02 Ex02 - Válida - Questão 9","status":"passed","title":"Ex02 - Válida - Questão 9","duration":0.17175599999995939,"failureMessages":[],"meta":{}},{"ancestorTitles":["Exercício 02"],"fullName":"Exercício 02 Ex02 - Correta - Questão 9","status":"passed","title":"Ex02 - Correta - Questão 9","duration":0.11148300000002109,"failureMessages":[],"meta":{}},{"ancestorTitles":["Exercício 02"],"fullName":"Exercício 02 Ex02 - Válida - Questão 10","status":"passed","title":"Ex02 - Válida - Questão 10","duration":0.18535499999995864,"failureMessages":[],"meta":{}},{"ancestorTitles":["Exercício 02"],"fullName":"Exercício 02 Ex02 - Correta - Questão 10","status":"passed","title":"Ex02 - Correta - Questão 10","duration":0.12047800000004827,"failureMessages":[],"meta":{}},{"ancestorTitles":["Exercício 02"],"fullName":"Exercício 02 Ex02 - Válida - Questão 11","status":"passed","title":"Ex02 - Válida - Questão 11","duration":0.192929999999933,"failureMessages":[],"meta":{}},{"ancestorTitles":["Exercício 02"],"fullName":"Exercício 02 Ex02 - Correta - Questão 11","status":"passed","title":"Ex02 - Correta - Questão 11","duration":0.12488200000007055,"failureMessages":[],"meta":{}},{"ancestorTitles":["Exercício 02"],"fullName":"Exercício 02 Ex02 - Válida - Questão 12","status":"passed","title":"Ex02 - Válida - Questão 12","duration":0.20713399999999638,"failureMessages":[],"meta":{}},{"ancestorTitles":["Exercício 02"],"fullName":"Exercício 02 Ex02 - Correta - Questão 12","status":"passed","title":"Ex02 - Correta - Questão 12","duration":0.1713560000000598,"failureMessages":[],"meta":{}},{"ancestorTitles":["Exercício 02"],"fullName":"Exercício 02 Ex02 - Válida - Questão 13","status":"passed","title":"Ex02 - Válida - Questão 13","duration":0.21535799999992378,"failureMessages":[],"meta":{}},{"ancestorTitles":["Exercício 02"],"fullName":"Exercício 02 Ex02 - Correta - Questão 13","status":"passed","title":"Ex02 - Correta - Questão 13","duration":0.11812000000008993,"failureMessages":[],"meta":{}},{"ancestorTitles":["Exercício 02"],"fullName":"Exercício 02 Ex02 - Válida - Questão 14","status":"passed","title":"Ex02 - Válida - Questão 14","duration":0.17508599999996477,"failureMessages":[],"meta":{}},{"ancestorTitles":["Exercício 02"],"fullName":"Exercício 02 Ex02 - Correta - Questão 14","status":"passed","title":"Ex02 - Correta - Questão 14","duration":0.11851499999988846,"failureMessages":[],"meta":{}},{"ancestorTitles":["Exercício 02"],"fullName":"Exercício 02 Ex02 - Válida - Questão 15","status":"passed","title":"Ex02 - Válida - Questão 15","duration":0.1746859999999515,"failureMessages":[],"meta":{}},{"ancestorTitles":["Exercício 02"],"fullName":"Exercício 02 Ex02 - Correta - Questão 15","status":"passed","title":"Ex02 - Correta - Questão 15","duration":0.11528799999996409,"failureMessages":[],"meta":{}},{"ancestorTitles":["Exercício 02"],"fullName":"Exercício 02 Ex02 - Válida - Questão 16","status":"passed","title":"Ex02 - Válida - Questão 16","duration":0.18110200000000987,"failureMessages":[],"meta":{}},{"ancestorTitles":["Exercício 02"],"fullName":"Exercício 02 Ex02 - Correta - Questão 16","status":"passed","title":"Ex02 - Correta - Questão 16","duration":0.17540299999996023,"failureMessages":[],"meta":{}},{"ancestorTitles":["Exercício 02"],"fullName":"Exercício 02 Ex02 - Válida - Questão 17","status":"passed","title":"Ex02 - Válida - Questão 17","duration":0.22063600000001315,"failureMessages":[],"meta":{}},{"ancestorTitles":["Exercício 02"],"fullName":"Exercício 02 Ex02 - Correta - Questão 17","status":"passed","title":"Ex02 - Correta - Questão 17","duration":0.1903069999999616,"failureMessages":[],"meta":{}},{"ancestorTitles":["Exercício 02"],"fullName":"Exercício 02 Ex02 - Válida - Questão 18","status":"passed","title":"Ex02 - Válida - Questão 18","duration":0.2794930000000022,"failureMessages":[],"meta":{}},{"ancestorTitles":["Exercício 02"],"fullName":"Exercício 02 Ex02 - Correta - Questão 18","status":"passed","title":"Ex02 - Correta - Questão 18","duration":0.1266449999999395,"failureMessages":[],"meta":{}},{"ancestorTitles":["Exercício 02"],"fullName":"Exercício 02 Ex02 - Válida - Questão 19","status":"passed","title":"Ex02 - Válida - Questão 19","duration":0.1822389999999814,"failureMessages":[],"meta":{}},{"ancestorTitles":["Exercício 02"],"fullName":"Exercício 02 Ex02 - Correta - Questão 19","status":"passed","title":"Ex02 - Correta - Questão 19","duration":0.1148279999999886,"failureMessages":[],"meta":{}},{"ancestorTitles":["Exercício 02"],"fullName":"Exercício 02 Ex02 - Válida - Questão 20","status":"passed","title":"Ex02 - Válida - Questão 20","duration":0.20002900000008594,"failureMessages":[],"meta":{}},{"ancestorTitles":["Exercício 02"],"fullName":"Exercício 02 Ex02 - Correta - Questão 20","status":"passed","title":"Ex02 - Correta - Questão 20","duration":0.18140099999993708,"failureMessages":[],"meta":{}},{"ancestorTitles":["Exercício 03"],"fullName":"Exercício 03 ex03 - Válida - Questão 1","status":"passed","title":"ex03 - Válida - Questão 1","duration":0.32991499999991447,"failureMessages":[],"meta":{}},{"ancestorTitles":["Exercício 03"],"fullName":"Exercício 03 ex03 - Correta - Questão 1","status":"passed","title":"ex03 - Correta - Questão 1","duration":0.3065430000000333,"failureMessages":[],"meta":{}},{"ancestorTitles":["Exercício 03"],"fullName":"Exercício 03 ex03 - Válida - Questão 2","status":"passed","title":"ex03 - Válida - Questão 2","duration":0.27898099999993065,"failureMessages":[],"meta":{}},{"ancestorTitles":["Exercício 03"],"fullName":"Exercício 03 ex03 - Correta - Questão 2","status":"passed","title":"ex03 - Correta - Questão 2","duration":0.22038700000007339,"failureMessages":[],"meta":{}},{"ancestorTitles":["Exercício 03"],"fullName":"Exercício 03 ex03 - Válida - Questão 3","status":"passed","title":"ex03 - Válida - Questão 3","duration":0.21925799999996798,"failureMessages":[],"meta":{}},{"ancestorTitles":["Exercício 03"],"fullName":"Exercício 03 ex03 - Correta - Questão 3","status":"passed","title":"ex03 - Correta - Questão 3","duration":0.12530800000001818,"failureMessages":[],"meta":{}},{"ancestorTitles":["Exercício 03"],"fullName":"Exercício 03 ex03 - Válida - Questão 4","status":"passed","title":"ex03 - Válida - Questão 4","duration":0.21495400000003428,"failureMessages":[],"meta":{}},{"ancestorTitles":["Exercício 03"],"fullName":"Exercício 03 ex03 - Correta - Questão 4","status":"passed","title":"ex03 - Correta - Questão 4","duration":0.1436750000000302,"failureMessages":[],"meta":{}},{"ancestorTitles":["Exercício 03"],"fullName":"Exercício 03 ex03 - Válida - Questão 5","status":"passed","title":"ex03 - Válida - Questão 5","duration":0.2402519999999413,"failureMessages":[],"meta":{}},{"ancestorTitles":["Exercício 03"],"fullName":"Exercício 03 ex03 - Correta - Questão 5","status":"passed","title":"ex03 - Correta - Questão 5","duration":0.12211500000000797,"failureMessages":[],"meta":{}},{"ancestorTitles":["Exercício 03"],"fullName":"Exercício 03 ex03 - Válida - Questão 6","status":"passed","title":"ex03 - Válida - Questão 6","duration":0.17830700000001798,"failureMessages":[],"meta":{}},{"ancestorTitles":["Exercício 03"],"fullName":"Exercício 03 ex03 - Correta - Questão 6","status":"passed","title":"ex03 - Correta - Questão 6","duration":0.11872300000004543,"failureMessages":[],"meta":{}},{"ancestorTitles":["Exercício 03"],"fullName":"Exercício 03 ex03 - Válida - Questão 7","status":"passed","title":"ex03 - Válida - Questão 7","duration":0.17553299999997307,"failureMessages":[],"meta":{}},{"ancestorTitles":["Exercício 03"],"fullName":"Exercício 03 ex03 - Correta - Questão 7","status":"passed","title":"ex03 - Correta - Questão 7","duration":0.11769300000003113,"failureMessages":[],"meta":{}},{"ancestorTitles":["Exercício 03"],"fullName":"Exercício 03 ex03 - Válida - Questão 8","status":"passed","title":"ex03 - Válida - Questão 8","duration":0.17827299999999013,"failureMessages":[],"meta":{}},{"ancestorTitles":["Exercício 03"],"fullName":"Exercício 03 ex03 - Correta - Questão 8","status":"passed","title":"ex03 - Correta - Questão 8","duration":0.11683400000003985,"failureMessages":[],"meta":{}},{"ancestorTitles":["Exercício 03"],"fullName":"Exercício 03 ex03 - Válida - Questão 9","status":"passed","title":"ex03 - Válida - Questão 9","duration":0.31333999999992557,"failureMessages":[],"meta":{}},{"ancestorTitles":["Exercício 03"],"fullName":"Exercício 03 ex03 - Correta - Questão 9","status":"passed","title":"ex03 - Correta - Questão 9","duration":0.13786700000002838,"failureMessages":[],"meta":{}},{"ancestorTitles":["Exercício 03"],"fullName":"Exercício 03 ex03 - Válida - Questão 10","status":"passed","title":"ex03 - Válida - Questão 10","duration":0.2422709999999597,"failureMessages":[],"meta":{}},{"ancestorTitles":["Exercício 03"],"fullName":"Exercício 03 ex03 - Correta - Questão 10","status":"passed","title":"ex03 - Correta - Questão 10","duration":0.13634000000001834,"failureMessages":[],"meta":{}},{"ancestorTitles":["Exercício 04"],"fullName":"Exercício 04 ex04 - Válida - Questão 1","status":"passed","title":"ex04 - Válida - Questão 1","duration":0.26192600000001676,"failureMessages":[],"meta":{}},{"ancestorTitles":["Exercício 04"],"fullName":"Exercício 04 ex04 - Correta - Questão 1","status":"passed","title":"ex04 - Correta - Questão 1","duration":0.21241799999995692,"failureMessages":[],"meta":{}},{"ancestorTitles":["Exercício 04"],"fullName":"Exercício 04 ex04 - Válida - Questão 2","status":"passed","title":"ex04 - Válida - Questão 2","duration":0.19235100000003058,"failureMessages":[],"meta":{}},{"ancestorTitles":["Exercício 04"],"fullName":"Exercício 04 ex04 - Correta - Questão 2","status":"passed","title":"ex04 - Correta - Questão 2","duration":0.1219499999999698,"failureMessages":[],"meta":{}},{"ancestorTitles":["Exercício 04"],"fullName":"Exercício 04 ex04 - Válida - Questão 3","status":"passed","title":"ex04 - Válida - Questão 3","duration":0.17865900000003876,"failureMessages":[],"meta":{}},{"ancestorTitles":["Exercício 04"],"fullName":"Exercício 04 ex04 - Correta - Questão 3","status":"passed","title":"ex04 - Correta - Questão 3","duration":0.1180299999999761,"failureMessages":[],"meta":{}},{"ancestorTitles":["Exercício 04"],"fullName":"Exercício 04 ex04 - Válida - Questão 4","status":"passed","title":"ex04 - Válida - Questão 4","duration":0.1754439999999704,"failureMessages":[],"meta":{}},{"ancestorTitles":["Exercício 04"],"fullName":"Exercício 04 ex04 - Correta - Questão 4","status":"passed","title":"ex04 - Correta - Questão 4","duration":0.1404810000000225,"failureMessages":[],"meta":{}},{"ancestorTitles":["Exercício 04"],"fullName":"Exercício 04 ex04 - Válida - Questão 5","status":"passed","title":"ex04 - Válida - Questão 5","duration":0.211812000000009,"failureMessages":[],"meta":{}},{"ancestorTitles":["Exercício 04"],"fullName":"Exercício 04 ex04 - Correta - Questão 5","status":"passed","title":"ex04 - Correta - Questão 5","duration":0.1266769999999724,"failureMessages":[],"meta":{}},{"ancestorTitles":["Exercício 04"],"fullName":"Exercício 04 ex04 - Válida - Questão 6","status":"passed","title":"ex04 - Válida - Questão 6","duration":0.19055700000001252,"failureMessages":[],"meta":{}},{"ancestorTitles":["Exercício 04"],"fullName":"Exercício 04 ex04 - Correta - Questão 6","status":"passed","title":"ex04 - Correta - Questão 6","duration":0.12539800000001833,"failureMessages":[],"meta":{}},{"ancestorTitles":["Exercício 04"],"fullName":"Exercício 04 ex04 - Válida - Questão 7","status":"passed","title":"ex04 - Válida - Questão 7","duration":0.18889100000001235,"failureMessages":[],"meta":{}},{"ancestorTitles":["Exercício 04"],"fullName":"Exercício 04 ex04 - Correta - Questão 7","status":"passed","title":"ex04 - Correta - Questão 7","duration":0.12447200000008252,"failureMessages":[],"meta":{}},{"ancestorTitles":["Exercício 04"],"fullName":"Exercício 04 ex04 - Válida - Questão 8","status":"passed","title":"ex04 - Válida - Questão 8","duration":0.2542150000000447,"failureMessages":[],"meta":{}},{"ancestorTitles":["Exercício 04"],"fullName":"Exercício 04 ex04 - Correta - Questão 8","status":"passed","title":"ex04 - Correta - Questão 8","duration":0.16158299999995052,"failureMessages":[],"meta":{}},{"ancestorTitles":["Exercício 04"],"fullName":"Exercício 04 ex04 - Válida - Questão 9","status":"passed","title":"ex04 - Válida - Questão 9","duration":0.18577200000004268,"failureMessages":[],"meta":{}},{"ancestorTitles":["Exercício 04"],"fullName":"Exercício 04 ex04 - Correta - Questão 9","status":"passed","title":"ex04 - Correta - Questão 9","duration":0.12147600000002967,"failureMessages":[],"meta":{}},{"ancestorTitles":["Exercício 04"],"fullName":"Exercício 04 ex04 - Válida - Questão 10","status":"passed","title":"ex04 - Válida - Questão 10","duration":0.2014769999999544,"failureMessages":[],"meta":{}},{"ancestorTitles":["Exercício 04"],"fullName":"Exercício 04 ex04 - Correta - Questão 10","status":"passed","title":"ex04 - Correta - Questão 10","duration":0.15993300000002364,"failureMessages":[],"meta":{}},{"ancestorTitles":["Exercício 04"],"fullName":"Exercício 04 ex04 - Válida - Questão 11","status":"passed","title":"ex04 - Válida - Questão 11","duration":0.18333700000005138,"failureMessages":[],"meta":{}},{"ancestorTitles":["Exercício 04"],"fullName":"Exercício 04 ex04 - Correta - Questão 11","status":"passed","title":"ex04 - Correta - Questão 11","duration":0.12474399999996422,"failureMessages":[],"meta":{}},{"ancestorTitles":["Exercício 04"],"fullName":"Exercício 04 ex04 - Válida - Questão 12","status":"passed","title":"ex04 - Válida - Questão 12","duration":0.17382399999996778,"failureMessages":[],"meta":{}},{"ancestorTitles":["Exercício 04"],"fullName":"Exercício 04 ex04 - Correta - Questão 12","status":"passed","title":"ex04 - Correta - Questão 12","duration":0.11526199999991604,"failureMessages":[],"meta":{}},{"ancestorTitles":["Exercício 04"],"fullName":"Exercício 04 ex04 - Válida - Questão 13","status":"passed","title":"ex04 - Válida - Questão 13","duration":0.25476800000001276,"failureMessages":[],"meta":{}},{"ancestorTitles":["Exercício 04"],"fullName":"Exercício 04 ex04 - Correta - Questão 13","status":"passed","title":"ex04 - Correta - Questão 13","duration":0.11510699999996632,"failureMessages":[],"meta":{}},{"ancestorTitles":["Exercício 04"],"fullName":"Exercício 04 ex04 - Válida - Questão 14","status":"passed","title":"ex04 - Válida - Questão 14","duration":0.1772399999999834,"failureMessages":[],"meta":{}},{"ancestorTitles":["Exercício 04"],"fullName":"Exercício 04 ex04 - Correta - Questão 14","status":"passed","title":"ex04 - Correta - Questão 14","duration":0.1518630000000485,"failureMessages":[],"meta":{}},{"ancestorTitles":["Exercício 04"],"fullName":"Exercício 04 ex04 - Válida - Questão 15","status":"passed","title":"ex04 - Válida - Questão 15","duration":0.19945800000004965,"failureMessages":[],"meta":{}},{"ancestorTitles":["Exercício 04"],"fullName":"Exercício 04 ex04 - Correta - Questão 15","status":"passed","title":"ex04 - Correta - Questão 15","duration":0.11606099999994512,"failureMessages":[],"meta":{}},{"ancestorTitles":["Exercício 04"],"fullName":"Exercício 04 ex04 - Válida - Questão 16","status":"passed","title":"ex04 - Válida - Questão 16","duration":0.20757900000000973,"failureMessages":[],"meta":{}},{"ancestorTitles":["Exercício 04"],"fullName":"Exercício 04 ex04 - Correta - Questão 16","status":"passed","title":"ex04 - Correta - Questão 16","duration":0.11588500000004842,"failureMessages":[],"meta":{}},{"ancestorTitles":["Exercício 04"],"fullName":"Exercício 04 ex04 - Válida - Questão 17","status":"passed","title":"ex04 - Válida - Questão 17","duration":0.17769899999996142,"failureMessages":[],"meta":{}},{"ancestorTitles":["Exercício 04"],"fullName":"Exercício 04 ex04 - Correta - Questão 17","status":"passed","title":"ex04 - Correta - Questão 17","duration":0.11445399999990968,"failureMessages":[],"meta":{}},{"ancestorTitles":["Exercício 04"],"fullName":"Exercício 04 ex04 - Válida - Questão 18","status":"passed","title":"ex04 - Válida - Questão 18","duration":0.20321500000000015,"failureMessages":[],"meta":{}},{"ancestorTitles":["Exercício 04"],"fullName":"Exercício 04 ex04 - Correta - Questão 18","status":"passed","title":"ex04 - Correta - Questão 18","duration":0.1185729999999694,"failureMessages":[],"meta":{}},{"ancestorTitles":["Exercício 04"],"fullName":"Exercício 04 ex04 - Válida - Questão 19","status":"passed","title":"ex04 - Válida - Questão 19","duration":0.1987699999999677,"failureMessages":[],"meta":{}},{"ancestorTitles":["Exercício 04"],"fullName":"Exercício 04 ex04 - Correta - Questão 19","status":"passed","title":"ex04 - Correta - Questão 19","duration":0.20638100000007853,"failureMessages":[],"meta":{}},{"ancestorTitles":["Exercício 04"],"fullName":"Exercício 04 ex04 - Válida - Questão 20","status":"passed","title":"ex04 - Válida - Questão 20","duration":0.21101899999996476,"failureMessages":[],"meta":{}},{"ancestorTitles":["Exercício 04"],"fullName":"Exercício 04 ex04 - Correta - Questão 20","status":"passed","title":"ex04 - Correta - Questão 20","duration":0.1163850000000366,"failureMessages":[],"meta":{}},{"ancestorTitles":["Exercício 05"],"fullName":"Exercício 05 ex05 - Válida - Questão 1","status":"passed","title":"ex05 - Válida - Questão 1","duration":0.27535999999997784,"failureMessages":[],"meta":{}},{"ancestorTitles":["Exercício 05"],"fullName":"Exercício 05 ex05 - Correta - Questão 1","status":"passed","title":"ex05 - Correta - Questão 1","duration":0.49394699999993463,"failureMessages":[],"meta":{}},{"ancestorTitles":["Exercício 05"],"fullName":"Exercício 05 ex05 - Válida - Questão 2","status":"passed","title":"ex05 - Válida - Questão 2","duration":0.23867699999993874,"failureMessages":[],"meta":{}},{"ancestorTitles":["Exercício 05"],"fullName":"Exercício 05 ex05 - Correta - Questão 2","status":"passed","title":"ex05 - Correta - Questão 2","duration":0.15298799999993662,"failureMessages":[],"meta":{}},{"ancestorTitles":["Exercício 05"],"fullName":"Exercício 05 ex05 - Válida - Questão 3","status":"passed","title":"ex05 - Válida - Questão 3","duration":0.18256499999995413,"failureMessages":[],"meta":{}},{"ancestorTitles":["Exercício 05"],"fullName":"Exercício 05 ex05 - Correta - Questão 3","status":"passed","title":"ex05 - Correta - Questão 3","duration":0.1670689999999695,"failureMessages":[],"meta":{}},{"ancestorTitles":["Exercício 05"],"fullName":"Exercício 05 ex05 - Válida - Questão 4","status":"passed","title":"ex05 - Válida - Questão 4","duration":0.23336699999993016,"failureMessages":[],"meta":{}},{"ancestorTitles":["Exercício 05"],"fullName":"Exercício 05 ex05 - Correta - Questão 4","status":"passed","title":"ex05 - Correta - Questão 4","duration":0.16278999999997268,"failureMessages":[],"meta":{}},{"ancestorTitles":["Exercício 05"],"fullName":"Exercício 05 ex05 - Válida - Questão 5","status":"passed","title":"ex05 - Válida - Questão 5","duration":0.23917500000004566,"failureMessages":[],"meta":{}},{"ancestorTitles":["Exercício 05"],"fullName":"Exercício 05 ex05 - Correta - Questão 5","status":"passed","title":"ex05 - Correta - Questão 5","duration":0.16364399999997659,"failureMessages":[],"meta":{}},{"ancestorTitles":["Exercício 05"],"fullName":"Exercício 05 ex05 - Válida - Questão 6","status":"passed","title":"ex05 - Válida - Questão 6","duration":0.20550900000000638,"failureMessages":[],"meta":{}},{"ancestorTitles":["Exercício 05"],"fullName":"Exercício 05 ex05 - Correta - Questão 6","status":"passed","title":"ex05 - Correta - Questão 6","duration":0.1648529999999937,"failureMessages":[],"meta":{}},{"ancestorTitles":["Exercício 05"],"fullName":"Exercício 05 ex05 - Válida - Questão 7","status":"passed","title":"ex05 - Válida - Questão 7","duration":0.200162999999975,"failureMessages":[],"meta":{}},{"ancestorTitles":["Exercício 05"],"fullName":"Exercício 05 ex05 - Correta - Questão 7","status":"passed","title":"ex05 - Correta - Questão 7","duration":0.26251800000000003,"failureMessages":[],"meta":{}},{"ancestorTitles":["Exercício 05"],"fullName":"Exercício 05 ex05 - Válida - Questão 8","status":"passed","title":"ex05 - Válida - Questão 8","duration":0.3388999999999669,"failureMessages":[],"meta":{}},{"ancestorTitles":["Exercício 05"],"fullName":"Exercício 05 ex05 - Correta - Questão 8","status":"passed","title":"ex05 - Correta - Questão 8","duration":0.28448199999991175,"failureMessages":[],"meta":{}},{"ancestorTitles":["Exercício 05"],"fullName":"Exercício 05 ex05 - Válida - Questão 9","status":"passed","title":"ex05 - Válida - Questão 9","duration":0.3449870000000601,"failureMessages":[],"meta":{}},{"ancestorTitles":["Exercício 05"],"fullName":"Exercício 05 ex05 - Correta - Questão 9","status":"passed","title":"ex05 - Correta - Questão 9","duration":0.3088100000001077,"failureMessages":[],"meta":{}},{"ancestorTitles":["Exercício 05"],"fullName":"Exercício 05 ex05 - Válida - Questão 10","status":"passed","title":"ex05 - Válida - Questão 10","duration":0.564707999999996,"failureMessages":[],"meta":{}},{"ancestorTitles":["Exercício 05"],"fullName":"Exercício 05 ex05 - Correta - Questão 10","status":"passed","title":"ex05 - Correta - Questão 10","duration":0.32233900000005633,"failureMessages":[],"meta":{}}],"startTime":1773057413960,"endTime":1773057414056.3223,"status":"failed","message":"","name":"/home/vicmca/CodeProjects/School/materiais/atividades/3c-rev-01/exercicios.test.js"}]}